rtl/ecc_decoder.v
// ecc_decoder.v – SECDED (72,64) Hamming decoder
//
// Accepts a 72-bit codeword ({check_bits[7:0], data[63:0]}) that may
// contain single-bit or double-bit errors and produces:
//   - Corrected 64-bit data output
//   - Single-error flag (single-bit error corrected)
//   - Double-error flag (uncorrectable double-bit error detected)
//   - Raw 8-bit syndrome for diagnostics
//
// Interface (from docs/ARCHITECTURE.md §3.5):
//   dec_word_in   [71:0] – 72-bit word read from DRAM
//   dec_data_out  [63:0] – corrected 64-bit data
//   dec_single_err       – 1: single-bit error detected and corrected
//   dec_double_err       – 1: double-bit error detected (uncorrectable)
//   dec_syndrome   [7:0] – raw syndrome (syndrome[7]=overall parity)
//
// SECDED error-detection rules:
//   syndrome[7]=0, syndrome[6:0]=0  → no error
//   syndrome[7]=1                    → single-bit error (correct if data bit)
//   syndrome[7]=0, syndrome[6:0]≠0  → double-bit error (detected only)
//
// Purely combinational – no clock or reset required.

`default_nettype none

module ecc_decoder (
    input  wire [71:0] dec_word_in,
    output reg  [63:0] dec_data_out,
    output wire        dec_single_err,
    output wire        dec_double_err,
    output wire [7:0]  dec_syndrome
);

    // ---------------------------------------------------------------
    // Unpack received word
    // ---------------------------------------------------------------
    wire [7:0]  cb_r = dec_word_in[71:64];  // received check bits
    wire [63:0] d_r  = dec_word_in[63:0];   // received data bits

    // ---------------------------------------------------------------
    // Syndrome computation
    // syndrome[k] = cb_r[k] XOR (parity of data bits in group k)
    // If syndrome[6:0]==0 the codeword is consistent; the exact
    // non-zero value of syndrome[6:0] encodes the error bit position.
    // syndrome[7] = overall parity of all 72 bits.
    // ---------------------------------------------------------------
    wire [6:0] synd;

    assign synd[0] =
        cb_r[0]         ^
        d_r[0]  ^ d_r[1]  ^ d_r[3]  ^ d_r[4]  ^
        d_r[6]  ^ d_r[8]  ^ d_r[10] ^ d_r[11] ^
        d_r[13] ^ d_r[15] ^ d_r[17] ^ d_r[19] ^
        d_r[21] ^ d_r[23] ^ d_r[25] ^ d_r[26] ^
        d_r[28] ^ d_r[30] ^ d_r[32] ^ d_r[34] ^
        d_r[36] ^ d_r[38] ^ d_r[40] ^ d_r[42] ^
        d_r[44] ^ d_r[46] ^ d_r[48] ^ d_r[50] ^
        d_r[52] ^ d_r[54] ^ d_r[56] ^ d_r[57] ^
        d_r[59] ^ d_r[61] ^ d_r[63];

    assign synd[1] =
        cb_r[1]         ^
        d_r[0]  ^ d_r[2]  ^ d_r[3]  ^ d_r[5]  ^
        d_r[6]  ^ d_r[9]  ^ d_r[10] ^ d_r[12] ^
        d_r[13] ^ d_r[16] ^ d_r[17] ^ d_r[20] ^
        d_r[21] ^ d_r[24] ^ d_r[25] ^ d_r[27] ^
        d_r[28] ^ d_r[31] ^ d_r[32] ^ d_r[35] ^
        d_r[36] ^ d_r[39] ^ d_r[40] ^ d_r[43] ^
        d_r[44] ^ d_r[47] ^ d_r[48] ^ d_r[51] ^
        d_r[52] ^ d_r[55] ^ d_r[56] ^ d_r[58] ^
        d_r[59] ^ d_r[62] ^ d_r[63];

    assign synd[2] =
        cb_r[2]         ^
        d_r[1]  ^ d_r[2]  ^ d_r[3]  ^ d_r[7]  ^
        d_r[8]  ^ d_r[9]  ^ d_r[10] ^ d_r[14] ^
        d_r[15] ^ d_r[16] ^ d_r[17] ^ d_r[22] ^
        d_r[23] ^ d_r[24] ^ d_r[25] ^ d_r[29] ^
        d_r[30] ^ d_r[31] ^ d_r[32] ^ d_r[37] ^
        d_r[38] ^ d_r[39] ^ d_r[40] ^ d_r[45] ^
        d_r[46] ^ d_r[47] ^ d_r[48] ^ d_r[53] ^
        d_r[54] ^ d_r[55] ^ d_r[56] ^ d_r[60] ^
        d_r[61] ^ d_r[62] ^ d_r[63];

    assign synd[3] =
        cb_r[3]         ^
        d_r[4]  ^ d_r[5]  ^ d_r[6]  ^ d_r[7]  ^
        d_r[8]  ^ d_r[9]  ^ d_r[10] ^ d_r[18] ^
        d_r[19] ^ d_r[20] ^ d_r[21] ^ d_r[22] ^
        d_r[23] ^ d_r[24] ^ d_r[25] ^ d_r[33] ^
        d_r[34] ^ d_r[35] ^ d_r[36] ^ d_r[37] ^
        d_r[38] ^ d_r[39] ^ d_r[40] ^ d_r[49] ^
        d_r[50] ^ d_r[51] ^ d_r[52] ^ d_r[53] ^
        d_r[54] ^ d_r[55] ^ d_r[56];

    assign synd[4] =
        cb_r[4]         ^
        d_r[11] ^ d_r[12] ^ d_r[13] ^ d_r[14] ^
        d_r[15] ^ d_r[16] ^ d_r[17] ^ d_r[18] ^
        d_r[19] ^ d_r[20] ^ d_r[21] ^ d_r[22] ^
        d_r[23] ^ d_r[24] ^ d_r[25] ^ d_r[41] ^
        d_r[42] ^ d_r[43] ^ d_r[44] ^ d_r[45] ^
        d_r[46] ^ d_r[47] ^ d_r[48] ^ d_r[49] ^
        d_r[50] ^ d_r[51] ^ d_r[52] ^ d_r[53] ^
        d_r[54] ^ d_r[55] ^ d_r[56];

    assign synd[5] =
        cb_r[5]         ^
        d_r[26] ^ d_r[27] ^ d_r[28] ^ d_r[29] ^
        d_r[30] ^ d_r[31] ^ d_r[32] ^ d_r[33] ^
        d_r[34] ^ d_r[35] ^ d_r[36] ^ d_r[37] ^
        d_r[38] ^ d_r[39] ^ d_r[40] ^ d_r[41] ^
        d_r[42] ^ d_r[43] ^ d_r[44] ^ d_r[45] ^
        d_r[46] ^ d_r[47] ^ d_r[48] ^ d_r[49] ^
        d_r[50] ^ d_r[51] ^ d_r[52] ^ d_r[53] ^
        d_r[54] ^ d_r[55] ^ d_r[56];

    assign synd[6] =
        cb_r[6]         ^
        d_r[57] ^ d_r[58] ^ d_r[59] ^ d_r[60] ^
        d_r[61] ^ d_r[62] ^ d_r[63];

    // Overall parity (bit 7 of syndrome): XOR of all 72 received bits
    wire overall_parity = ^dec_word_in;

    assign dec_syndrome   = {overall_parity, synd};

    // SECDED rules:
    //   overall_parity==1               → single-bit error (syndrome[6:0] says where)
    //   overall_parity==0, synd!=0      → double-bit error
    assign dec_single_err = overall_parity;
    assign dec_double_err = (synd != 7'h0) & ~overall_parity;

    // ---------------------------------------------------------------
    // Single-bit error correction
    // syndrome[6:0] is the logical Hamming position of the error.
    // Powers-of-2 positions (1,2,4,8,16,32,64) mean a check-bit
    // error; data is already correct.  All other positions map to
    // a specific data bit which is flipped.
    // ---------------------------------------------------------------
    reg [63:0] corr_mask;

    always @(*) begin
        corr_mask = 64'h0;
        if (dec_single_err) begin
            case (synd)
                // Data bit positions (non-powers-of-2 in 1..71)
                7'd3:  corr_mask[0]  = 1'b1;
                7'd5:  corr_mask[1]  = 1'b1;
                7'd6:  corr_mask[2]  = 1'b1;
                7'd7:  corr_mask[3]  = 1'b1;
                7'd9:  corr_mask[4]  = 1'b1;
                7'd10: corr_mask[5]  = 1'b1;
                7'd11: corr_mask[6]  = 1'b1;
                7'd12: corr_mask[7]  = 1'b1;
                7'd13: corr_mask[8]  = 1'b1;
                7'd14: corr_mask[9]  = 1'b1;
                7'd15: corr_mask[10] = 1'b1;
                7'd17: corr_mask[11] = 1'b1;
                7'd18: corr_mask[12] = 1'b1;
                7'd19: corr_mask[13] = 1'b1;
                7'd20: corr_mask[14] = 1'b1;
                7'd21: corr_mask[15] = 1'b1;
                7'd22: corr_mask[16] = 1'b1;
                7'd23: corr_mask[17] = 1'b1;
                7'd24: corr_mask[18] = 1'b1;
                7'd25: corr_mask[19] = 1'b1;
                7'd26: corr_mask[20] = 1'b1;
                7'd27: corr_mask[21] = 1'b1;
                7'd28: corr_mask[22] = 1'b1;
                7'd29: corr_mask[23] = 1'b1;
                7'd30: corr_mask[24] = 1'b1;
                7'd31: corr_mask[25] = 1'b1;
                7'd33: corr_mask[26] = 1'b1;
                7'd34: corr_mask[27] = 1'b1;
                7'd35: corr_mask[28] = 1'b1;
                7'd36: corr_mask[29] = 1'b1;
                7'd37: corr_mask[30] = 1'b1;
                7'd38: corr_mask[31] = 1'b1;
                7'd39: corr_mask[32] = 1'b1;
                7'd40: corr_mask[33] = 1'b1;
                7'd41: corr_mask[34] = 1'b1;
                7'd42: corr_mask[35] = 1'b1;
                7'd43: corr_mask[36] = 1'b1;
                7'd44: corr_mask[37] = 1'b1;
                7'd45: corr_mask[38] = 1'b1;
                7'd46: corr_mask[39] = 1'b1;
                7'd47: corr_mask[40] = 1'b1;
                7'd48: corr_mask[41] = 1'b1;
                7'd49: corr_mask[42] = 1'b1;
                7'd50: corr_mask[43] = 1'b1;
                7'd51: corr_mask[44] = 1'b1;
                7'd52: corr_mask[45] = 1'b1;
                7'd53: corr_mask[46] = 1'b1;
                7'd54: corr_mask[47] = 1'b1;
                7'd55: corr_mask[48] = 1'b1;
                7'd56: corr_mask[49] = 1'b1;
                7'd57: corr_mask[50] = 1'b1;
                7'd58: corr_mask[51] = 1'b1;
                7'd59: corr_mask[52] = 1'b1;
                7'd60: corr_mask[53] = 1'b1;
                7'd61: corr_mask[54] = 1'b1;
                7'd62: corr_mask[55] = 1'b1;
                7'd63: corr_mask[56] = 1'b1;
                7'd65: corr_mask[57] = 1'b1;
                7'd66: corr_mask[58] = 1'b1;
                7'd67: corr_mask[59] = 1'b1;
                7'd68: corr_mask[60] = 1'b1;
                7'd69: corr_mask[61] = 1'b1;
                7'd70: corr_mask[62] = 1'b1;
                7'd71: corr_mask[63] = 1'b1;
                // Check-bit error positions (1,2,4,8,16,32,64) or cb[7] (synd=0):
                // data is already correct; corr_mask stays 0
                default: corr_mask = 64'h0;
            endcase
        end
    end

    // Apply correction mask to received data
    always @(*) begin
        dec_data_out = d_r ^ corr_mask;
    end

endmodule

`default_nettype wire

tb/ecc_decoder_tb.v
// ecc_decoder_tb.v – Testbench for ecc_decoder (SECDED 72,64)
//
// Tests:
//   1. No-error case: valid codeword passes through (no flags, data correct)
//   2. All 72 single-bit error positions: single_err=1, double_err=0,
//      data corrected (for data-bit errors) or unchanged (for check-bit errors)
//   3. Selected double-bit errors: single_err=0, double_err=1
//   4. cb[7]-only error (syndrome[6:0]=0, overall_parity=1): single_err=1
//
// Compile & run:
//   iverilog -g2012 -o build/ecc_decoder.out tb/ecc_decoder_tb.v rtl/ecc_decoder.v
//   vvp build/ecc_decoder.out

`timescale 1ns/1ps

module ecc_decoder_tb;

    // ----------------------------------------------------------------
    // DUT wires
    // ----------------------------------------------------------------
    reg  [71:0] dec_word_in;
    wire [63:0] dec_data_out;
    wire        dec_single_err;
    wire        dec_double_err;
    wire [7:0]  dec_syndrome;

    ecc_decoder dut (
        .dec_word_in   (dec_word_in),
        .dec_data_out  (dec_data_out),
        .dec_single_err(dec_single_err),
        .dec_double_err(dec_double_err),
        .dec_syndrome  (dec_syndrome)
    );

    // ----------------------------------------------------------------
    // VCD dump
    // ----------------------------------------------------------------
    initial begin
        $dumpfile("results/phase-ddr4-ecc/ecc_decoder.vcd");
        $dumpvars(0, ecc_decoder_tb);
    end

    // ----------------------------------------------------------------
    // Reference encoder (same logic as ecc_encoder.v) for building
    // valid codewords without depending on the encoder module.
    // ----------------------------------------------------------------
    function [7:0] ref_check_bits;
        input [63:0] d;
        reg [6:0] c;
        begin
            c[0] = d[0]^d[1]^d[3]^d[4]^d[6]^d[8]^d[10]^d[11]^d[13]^d[15]^
                   d[17]^d[19]^d[21]^d[23]^d[25]^d[26]^d[28]^d[30]^d[32]^d[34]^
                   d[36]^d[38]^d[40]^d[42]^d[44]^d[46]^d[48]^d[50]^d[52]^d[54]^
                   d[56]^d[57]^d[59]^d[61]^d[63];
            c[1] = d[0]^d[2]^d[3]^d[5]^d[6]^d[9]^d[10]^d[12]^d[13]^d[16]^
                   d[17]^d[20]^d[21]^d[24]^d[25]^d[27]^d[28]^d[31]^d[32]^d[35]^
                   d[36]^d[39]^d[40]^d[43]^d[44]^d[47]^d[48]^d[51]^d[52]^d[55]^
                   d[56]^d[58]^d[59]^d[62]^d[63];
            c[2] = d[1]^d[2]^d[3]^d[7]^d[8]^d[9]^d[10]^d[14]^d[15]^d[16]^
                   d[17]^d[22]^d[23]^d[24]^d[25]^d[29]^d[30]^d[31]^d[32]^d[37]^
                   d[38]^d[39]^d[40]^d[45]^d[46]^d[47]^d[48]^d[53]^d[54]^d[55]^
                   d[56]^d[60]^d[61]^d[62]^d[63];
            c[3] = d[4]^d[5]^d[6]^d[7]^d[8]^d[9]^d[10]^d[18]^d[19]^d[20]^
                   d[21]^d[22]^d[23]^d[24]^d[25]^d[33]^d[34]^d[35]^d[36]^d[37]^
                   d[38]^d[39]^d[40]^d[49]^d[50]^d[51]^d[52]^d[53]^d[54]^d[55]^
                   d[56];
            c[4] = d[11]^d[12]^d[13]^d[14]^d[15]^d[16]^d[17]^d[18]^d[19]^
                   d[20]^d[21]^d[22]^d[23]^d[24]^d[25]^d[41]^d[42]^d[43]^d[44]^
                   d[45]^d[46]^d[47]^d[48]^d[49]^d[50]^d[51]^d[52]^d[53]^d[54]^
                   d[55]^d[56];
            c[5] = d[26]^d[27]^d[28]^d[29]^d[30]^d[31]^d[32]^d[33]^d[34]^
                   d[35]^d[36]^d[37]^d[38]^d[39]^d[40]^d[41]^d[42]^d[43]^d[44]^
                   d[45]^d[46]^d[47]^d[48]^d[49]^d[50]^d[51]^d[52]^d[53]^d[54]^
                   d[55]^d[56];
            c[6] = d[57]^d[58]^d[59]^d[60]^d[61]^d[62]^d[63];
            ref_check_bits = {(^d ^ ^c), c};
        end
    endfunction

    function [71:0] ref_encode;
        input [63:0] d;
        begin
            ref_encode = {ref_check_bits(d), d};
        end
    endfunction

    // ----------------------------------------------------------------
    // Test counters
    // ----------------------------------------------------------------
    integer pass_count, fail_count;
    integer bit_pos;
    reg [71:0] codeword, corrupted;
    reg [63:0] test_data;

    // ----------------------------------------------------------------
    // Test execution
    // ----------------------------------------------------------------
    initial begin
        pass_count = 0;
        fail_count = 0;

        // ==============================================================
        // Test 1: No error – valid codeword passes through unchanged
        // ==============================================================
        test_data   = 64'hDEADBEEFCAFEBABE;
        codeword    = ref_encode(test_data);
        dec_word_in = codeword;
        #1;
        if (dec_data_out !== test_data) begin
            $display("FAIL T1: no-error data mismatch: got %h exp %h",
                     dec_data_out, test_data);
            fail_count = fail_count + 1;
        end else if (dec_single_err !== 1'b0 || dec_double_err !== 1'b0) begin
            $display("FAIL T1: error flags set on valid codeword se=%b de=%b",
                     dec_single_err, dec_double_err);
            fail_count = fail_count + 1;
        end else begin
            $display("PASS T1: no-error: data=0x%016x se=0 de=0", test_data);
            pass_count = pass_count + 1;
        end

        // ==============================================================
        // Test 2: All 64 data-bit single-bit error injections
        // ==============================================================
        $display("Running all 64 data-bit single-bit error corrections...");
        test_data = 64'hDEADBEEFCAFEBABE;
        codeword  = ref_encode(test_data);

        for (bit_pos = 0; bit_pos < 64; bit_pos = bit_pos + 1) begin
            corrupted   = codeword ^ (72'h1 << bit_pos);
            dec_word_in = corrupted;
            #1;
            if (dec_single_err !== 1'b1) begin
                $display("FAIL T2 bit=%0d: single_err not set", bit_pos);
                fail_count = fail_count + 1;
            end else if (dec_double_err !== 1'b0) begin
                $display("FAIL T2 bit=%0d: double_err incorrectly set", bit_pos);
                fail_count = fail_count + 1;
            end else if (dec_data_out !== test_data) begin
                $display("FAIL T2 bit=%0d: data not corrected, got %h exp %h",
                         bit_pos, dec_data_out, test_data);
                fail_count = fail_count + 1;
            end else begin
                pass_count = pass_count + 1;
            end
        end
        $display("PASS T2: all 64 data-bit single-error corrections OK");

        // ==============================================================
        // Test 3: Check-bit single-bit error injections (bits 64..71)
        //   Data must come out unchanged; single_err=1, double_err=0
        // ==============================================================
        $display("Running 8 check-bit single-bit error corrections...");
        for (bit_pos = 64; bit_pos < 72; bit_pos = bit_pos + 1) begin
            corrupted   = codeword ^ (72'h1 << bit_pos);
            dec_word_in = corrupted;
            #1;
            if (dec_single_err !== 1'b1) begin
                $display("FAIL T3 cbit=%0d: single_err not set", bit_pos - 64);
                fail_count = fail_count + 1;
            end else if (dec_double_err !== 1'b0) begin
                $display("FAIL T3 cbit=%0d: double_err incorrectly set", bit_pos - 64);
                fail_count = fail_count + 1;
            end else if (dec_data_out !== test_data) begin
                $display("FAIL T3 cbit=%0d: data changed on check-bit error",
                         bit_pos - 64);
                fail_count = fail_count + 1;
            end else begin
                pass_count = pass_count + 1;
            end
        end
        $display("PASS T3: all 8 check-bit single-error detections OK");

        // ==============================================================
        // Test 4: Double-bit error detection (sample: 16 pairs)
        // ==============================================================
        $display("Running double-bit error detection checks (sample pairs)...");
        begin
            integer i, j;
            integer dbl_pass;
            dbl_pass = 0;
            for (i = 0; i < 72; i = i + 9) begin
                for (j = i + 1; j < 72; j = j + 7) begin
                    corrupted   = codeword ^ (72'h1 << i) ^ (72'h1 << j);
                    dec_word_in = corrupted;
                    #1;
                    if (dec_double_err !== 1'b1 || dec_single_err !== 1'b0) begin
                        $display("FAIL T4 bits=%0d,%0d: de=%b se=%b",
                                 i, j, dec_double_err, dec_single_err);
                        fail_count = fail_count + 1;
                    end else begin
                        dbl_pass = dbl_pass + 1;
                        pass_count = pass_count + 1;
                    end
                end
            end
            $display("PASS T4: %0d double-bit error pairs detected correctly",
                     dbl_pass);
        end

        // ==============================================================
        // Test 5: Multiple data words – no error round-trip
        // ==============================================================
        $display("Running 6 no-error round-trip checks...");
        begin
            integer k;
            reg [63:0] tv [0:5];
            tv[0] = 64'h0;
            tv[1] = 64'hFFFFFFFFFFFFFFFF;
            tv[2] = 64'h5555555555555555;
            tv[3] = 64'hAAAAAAAAAAAAAAAA;
            tv[4] = 64'h123456789ABCDEF0;
            tv[5] = 64'hFEDCBA9876543210;
            for (k = 0; k < 6; k = k + 1) begin
                dec_word_in = ref_encode(tv[k]);
                #1;
                if (dec_data_out !== tv[k] || dec_single_err || dec_double_err) begin
                    $display("FAIL T5[%0d]: d=%016x se=%b de=%b got=%016x",
                             k, tv[k], dec_single_err, dec_double_err, dec_data_out);
                    fail_count = fail_count + 1;
                end else begin
                    pass_count = pass_count + 1;
                end
            end
            $display("PASS T5: 6 no-error round-trips OK");
        end

        // ==============================================================
        // Summary
        // ==============================================================
        $display("--------------------------------------------");
        $display("ecc_decoder_tb: %0d PASSED, %0d FAILED", pass_count, fail_count);
        $display("--------------------------------------------");
        if (fail_count != 0) $fatal(1, "ecc_decoder_tb: simulation FAILED");
        $finish;
    end

endmodule

results/phase-ddr4-ecc/ecc_decoder.vcd
$date
	Thu Mar 12 09:46:30 2026
$end
$version
	Icarus Verilog
$end
$timescale
	1ps
$end
$scope module ecc_decoder_tb $end
$var wire 8 ! dec_syndrome [7:0] $end
$var wire 1 " dec_single_err $end
$var wire 1 # dec_double_err $end
$var wire 64 $ dec_data_out [63:0] $end
$var reg 72 % codeword [71:0] $end
$var reg 72 & corrupted [71:0] $end
$var reg 72 ' dec_word_in [71:0] $end
$var reg 64 ( test_data [63:0] $end
$var integer 32 ) bit_pos [31:0] $end
$var integer 32 * fail_count [31:0] $end
$var integer 32 + pass_count [31:0] $end
$scope function ref_check_bits $end
$var reg 7 , c [6:0] $end
$var reg 64 - d [63:0] $end
$upscope $end
$scope function ref_encode $end
$var reg 64 . d [63:0] $end
$upscope $end
$scope module dut $end
$var wire 1 # dec_double_err $end
$var wire 1 " dec_single_err $end
$var wire 72 / dec_word_in [71:0] $end
$var wire 7 0 synd [6:0] $end
$var wire 1 1 overall_parity $end
$var wire 8 2 dec_syndrome [7:0] $end
$var wire 64 3 d_r [63:0] $end
$var wire 8 4 cb_r [7:0] $end
$var reg 64 5 corr_mask [63:0] $end
$var reg 64 6 dec_data_out [63:0] $end
$upscope $end
$scope begin $unm_blk_18 $end
$var integer 32 7 dbl_pass [31:0] $end
$var integer 32 8 i [31:0] $end
$var integer 32 9 j [31:0] $end
$upscope $end
$scope begin $unm_blk_23 $end
$var integer 32 : k [31:0] $end
$upscope $end
$upscope $end
$enddefinitions $end
$comment Show the parameter values. $end
$dumpall
$end
#0
$dumpvars
bx :
bx 9
bx 8
bx 7
b1101111010101101101111101110111111001010111111101011101010111110 6
b0 5
b111010 4
b1101111010101101101111101110111111001010111111101011101010111110 3
b0 2
01
b0 0
b1110101101111010101101101111101110111111001010111111101011101010111110 /
b1101111010101101101111101110111111001010111111101011101010111110 .
b1101111010101101101111101110111111001010111111101011101010111110 -
b111010 ,
b0 +
b0 *
bx )
b1101111010101101101111101110111111001010111111101011101010111110 (
b1110101101111010101101101111101110111111001010111111101011101010111110 '
bx &
b1110101101111010101101101111101110111111001010111111101011101010111110 %
b1101111010101101101111101110111111001010111111101011101010111110 $
0#
0"
b0 !
$end
#1000
b1 5
b11 0
b1101111010101101101111101110111111001010111111101011101010111110 $
b1101111010101101101111101110111111001010111111101011101010111110 6
b1101111010101101101111101110111111001010111111101011101010111111 3
b10000011 !
b10000011 2
1"
11
b1110101101111010101101101111101110111111001010111111101011101010111111 '
b1110101101111010101101101111101110111111001010111111101011101010111111 /
b1110101101111010101101101111101110111111001010111111101011101010111111 &
b0 )
b1 +
#2000
b10 5
b10000101 !
b10000101 2
b101 0
b1101111010101101101111101110111111001010111111101011101010111110 $
b1101111010101101101111101110111111001010111111101011101010111110 6
b1101111010101101101111101110111111001010111111101011101010111100 3
b1110101101111010101101101111101110111111001010111111101011101010111100 '
b1110101101111010101101101111101110111111001010111111101011101010111100 /
b1110101101111010101101101111101110111111001010111111101011101010111100 &
b1 )
b10 +
#3000
b100 5
b10000110 !
b10000110 2
b110 0
b1101111010101101101111101110111111001010111111101011101010111110 $
b1101111010101101101111101110111111001010111111101011101010111110 6
b1101111010101101101111101110111111001010111111101011101010111010 3
b1110101101111010101101101111101110111111001010111111101011101010111010 '
b1110101101111010101101101111101110111111001010111111101011101010111010 /
b1110101101111010101101101111101110111111001010111111101011101010111010 &
b10 )
b11 +
#4000
b1000 5
b10000111 !
b10000111 2
b111 0
b1101111010101101101111101110111111001010111111101011101010111110 $
b1101111010101101101111101110111111001010111111101011101010111110 6
b1101111010101101101111101110111111001010111111101011101010110110 3
b1110101101111010101101101111101110111111001010111111101011101010110110 '
b1110101101111010101101101111101110111111001010111111101011101010110110 /
b1110101101111010101101101111101110111111001010111111101011101010110110 &
b11 )
b100 +
#5000
b10000 5
b10001001 !
b10001001 2
b1001 0
b1101111010101101101111101110111111001010111111101011101010111110 $
b1101111010101101101111101110111111001010111111101011101010111110 6
b1101111010101101101111101110111111001010111111101011101010101110 3
b1110101101111010101101101111101110111111001010111111101011101010101110 '
b1110101101111010101101101111101110111111001010111111101011101010101110 /
b1110101101111010101101101111101110111111001010111111101011101010101110 &
b100 )
b101 +
#6000
b100000 5
b10001010 !
b10001010 2
b1010 0
b1101111010101101101111101110111111001010111111101011101010111110 $
b1101111010101101101111101110111111001010111111101011101010111110 6
b1101111010101101101111101110111111001010111111101011101010011110 3
b1110101101111010101101101111101110111111001010111111101011101010011110 '
b1110101101111010101101101111101110111111001010111111101011101010011110 /
b1110101101111010101101101111101110111111001010111111101011101010011110 &
b101 )
b110 +
#7000
b1000000 5
b10001011 !
b10001011 2
b1011 0
b1101111010101101101111101110111111001010111111101011101010111110 $
b1101111010101101101111101110111111001010111111101011101010111110 6
b1101111010101101101111101110111111001010111111101011101011111110 3
b1110101101111010101101101111101110111111001010111111101011101011111110 '
b1110101101111010101101101111101110111111001010111111101011101011111110 /
b1110101101111010101101101111101110111111001010111111101011101011111110 &
b110 )
b111 +
#8000
b10000000 5
b10001100 !
b10001100 2
b1100 0
b1101111010101101101111101110111111001010111111101011101010111110 $
b1101111010101101101111101110111111001010111111101011101010111110 6
b1101111010101101101111101110111111001010111111101011101000111110 3
b1110101101111010101101101111101110111111001010111111101011101000111110 '
b1110101101111010101101101111101110111111001010111111101011101000111110 /
b1110101101111010101101101111101110111111001010111111101011101000111110 &
b111 )
b1000 +
#9000
b100000000 5
b10001101 !
b10001101 2
b1101 0
b1101111010101101101111101110111111001010111111101011101010111110 $
b1101111010101101101111101110111111001010111111101011101010111110 6
b1101111010101101101111101110111111001010111111101011101110111110 3
b1110101101111010101101101111101110111111001010111111101011101110111110 '
b1110101101111010101101101111101110111111001010111111101011101110111110 /
b1110101101111010101101101111101110111111001010111111101011101110111110 &
b1000 )
b1001 +
#10000
b1000000000 5
b10001110 !
b10001110 2
b1110 0
b1101111010101101101111101110111111001010111111101011101010111110 $
b1101111010101101101111101110111111001010111111101011101010111110 6
b1101111010101101101111101110111111001010111111101011100010111110 3
b1110101101111010101101101111101110111111001010111111101011100010111110 '
b1110101101111010101101101111101110111111001010111111101011100010111110 /
b1110101101111010101101101111101110111111001010111111101011100010111110 &
b1001 )
b1010 +
#11000
b10000000000 5
b10001111 !
b10001111 2
b1111 0
b1101111010101101101111101110111111001010111111101011101010111110 $
b1101111010101101101111101110111111001010111111101011101010111110 6
b1101111010101101101111101110111111001010111111101011111010111110 3
b1110101101111010101101101111101110111111001010111111101011111010111110 '
b1110101101111010101101101111101110111111001010111111101011111010111110 /
b1110101101111010101101101111101110111111001010111111101011111010111110 &
b1010 )
b1011 +
#12000
b100000000000 5
b10010001 !
b10010001 2
b10001 0
b1101111010101101101111101110111111001010111111101011101010111110 $
b1101111010101101101111101110111111001010111111101011101010111110 6
b1101111010101101101111101110111111001010111111101011001010111110 3
b1110101101111010101101101111101110111111001010111111101011001010111110 '
b1110101101111010101101101111101110111111001010111111101011001010111110 /
b1110101101111010101101101111101110111111001010111111101011001010111110 &
b1011 )
b1100 +
#13000
b1000000000000 5
b10010010 !
b10010010 2
b10010 0
b1101111010101101101111101110111111001010111111101011101010111110 $
b1101111010101101101111101110111111001010111111101011101010111110 6
b1101111010101101101111101110111111001010111111101010101010111110 3
b1110101101111010101101101111101110111111001010111111101010101010111110 '
b1110101101111010101101101111101110111111001010111111101010101010111110 /
b1110101101111010101101101111101110111111001010111111101010101010111110 &
b1100 )
b1101 +
#14000
b10000000000000 5
b10010011 !
b10010011 2
b10011 0
b1101111010101101101111101110111111001010111111101011101010111110 $
b1101111010101101101111101110111111001010111111101011101010111110 6
b1101111010101101101111101110111111001010111111101001101010111110 3
b1110101101111010101101101111101110111111001010111111101001101010111110 '
b1110101101111010101101101111101110111111001010111111101001101010111110 /
b1110101101111010101101101111101110111111001010111111101001101010111110 &
b1101 )
b1110 +
#15000
b100000000000000 5
b10010100 !
b10010100 2
b10100 0
b1101111010101101101111101110111111001010111111101011101010111110 $
b1101111010101101101111101110111111001010111111101011101010111110 6
b1101111010101101101111101110111111001010111111101111101010111110 3
b1110101101111010101101101111101110111111001010111111101111101010111110 '
b1110101101111010101101101111101110111111001010111111101111101010111110 /
b1110101101111010101101101111101110111111001010111111101111101010111110 &
b1110 )
b1111 +
#16000
b1000000000000000 5
b10010101 !
b10010101 2
b10101 0
b1101111010101101101111101110111111001010111111101011101010111110 $
b1101111010101101101111101110111111001010111111101011101010111110 6
b1101111010101101101111101110111111001010111111100011101010111110 3
b1110101101111010101101101111101110111111001010111111100011101010111110 '
b1110101101111010101101101111101110111111001010111111100011101010111110 /
b1110101101111010101101101111101110111111001010111111100011101010111110 &
b1111 )
b10000 +
#17000
b10000000000000000 5
b10010110 !
b10010110 2
b10110 0
b1101111010101101101111101110111111001010111111101011101010111110 $
b1101111010101101101111101110111111001010111111101011101010111110 6
b1101111010101101101111101110111111001010111111111011101010111110 3
b1110101101111010101101101111101110111111001010111111111011101010111110 '
b1110101101111010101101101111101110111111001010111111111011101010111110 /
b1110101101111010101101101111101110111111001010111111111011101010111110 &
b10000 )
b10001 +
#18000
b100000000000000000 5
b10010111 !
b10010111 2
b10111 0
b1101111010101101101111101110111111001010111111101011101010111110 $
b1101111010101101101111101110111111001010111111101011101010111110 6
b1101111010101101101111101110111111001010111111001011101010111110 3
b1110101101111010101101101111101110111111001010111111001011101010111110 '
b1110101101111010101101101111101110111111001010111111001011101010111110 /
b1110101101111010101101101111101110111111001010111111001011101010111110 &
b10001 )
b10010 +
#19000
b1000000000000000000 5
b10011000 !
b10011000 2
b11000 0
b1101111010101101101111101110111111001010111111101011101010111110 $
b1101111010101101101111101110111111001010111111101011101010111110 6
b1101111010101101101111101110111111001010111110101011101010111110 3
b1110101101111010101101101111101110111111001010111110101011101010111110 '
b1110101101111010101101101111101110111111001010111110101011101010111110 /
b1110101101111010101101101111101110111111001010111110101011101010111110 &
b10010 )
b10011 +
#20000
b10000000000000000000 5
b10011001 !
b10011001 2
b11001 0
b1101111010101101101111101110111111001010111111101011101010111110 $
b1101111010101101101111101110111111001010111111101011101010111110 6
b1101111010101101101111101110111111001010111101101011101010111110 3
b1110101101111010101101101111101110111111001010111101101011101010111110 '
b1110101101111010101101101111101110111111001010111101101011101010111110 /
b1110101101111010101101101111101110111111001010111101101011101010111110 &
b10011 )
b10100 +
#21000
b100000000000000000000 5
b10011010 !
b10011010 2
b11010 0
b1101111010101101101111101110111111001010111111101011101010111110 $
b1101111010101101101111101110111111001010111111101011101010111110 6
b1101111010101101101111101110111111001010111011101011101010111110 3
b1110101101111010101101101111101110111111001010111011101011101010111110 '
b1110101101111010101101101111101110111111001010111011101011101010111110 /
b1110101101111010101101101111101110111111001010111011101011101010111110 &
b10100 )
b10101 +
#22000
b1000000000000000000000 5
b10011011 !
b10011011 2
b11011 0
b1101111010101101101111101110111111001010111111101011101010111110 $
b1101111010101101101111101110111111001010111111101011101010111110 6
b1101111010101101101111101110111111001010110111101011101010111110 3
b1110101101111010101101101111101110111111001010110111101011101010111110 '
b1110101101111010101101101111101110111111001010110111101011101010111110 /
b1110101101111010101101101111101110111111001010110111101011101010111110 &
b10101 )
b10110 +
