rtl/ecc_encoder.v
// ecc_encoder.v – SECDED (72,64) Hamming encoder
//
// Generates 8 check bits for a 64-bit data word using a standard
// Single-Error-Correcting, Double-Error-Detecting (SECDED) code.
//
// Data bits d[0..63] occupy non-power-of-2 positions 1..71 in the
// logical Hamming codeword.  Check bits cb[0..6] sit at the seven
// power-of-2 positions (1, 2, 4, 8, 16, 32, 64) and cb[7] is an
// overall parity bit that enables double-error detection.
//
// Interface (from docs/ARCHITECTURE.md §3.4):
//   enc_data_in  [63:0]  – raw 64-bit write data
//   enc_check_out [7:0]  – 8 SECDED check bits
//   enc_word_out [71:0]  – {enc_check_out, enc_data_in}
//
// Purely combinational – no clock or reset required.

`default_nettype none

module ecc_encoder (
    input  wire [63:0] enc_data_in,
    output wire [7:0]  enc_check_out,
    output wire [71:0] enc_word_out
);

    // ---------------------------------------------------------------
    // Check bit generation
    // Each cb[k] (k=0..6) is the even-parity bit over all data bits
    // whose logical Hamming position has bit k set.
    // Logical positions of d[0]..d[63]:
    //   d[0..3]   -> 3, 5, 6, 7
    //   d[4..10]  -> 9..15
    //   d[11..25] -> 17..31
    //   d[26..56] -> 33..63
    //   d[57..63] -> 65..71
    // ---------------------------------------------------------------

    // cb[0]: covers positions where bit 0 is set (odd positions 3,5,7,…,71)
    assign enc_check_out[0] =
        enc_data_in[0]  ^ enc_data_in[1]  ^ enc_data_in[3]  ^ enc_data_in[4]  ^
        enc_data_in[6]  ^ enc_data_in[8]  ^ enc_data_in[10] ^ enc_data_in[11] ^
        enc_data_in[13] ^ enc_data_in[15] ^ enc_data_in[17] ^ enc_data_in[19] ^
        enc_data_in[21] ^ enc_data_in[23] ^ enc_data_in[25] ^ enc_data_in[26] ^
        enc_data_in[28] ^ enc_data_in[30] ^ enc_data_in[32] ^ enc_data_in[34] ^
        enc_data_in[36] ^ enc_data_in[38] ^ enc_data_in[40] ^ enc_data_in[42] ^
        enc_data_in[44] ^ enc_data_in[46] ^ enc_data_in[48] ^ enc_data_in[50] ^
        enc_data_in[52] ^ enc_data_in[54] ^ enc_data_in[56] ^ enc_data_in[57] ^
        enc_data_in[59] ^ enc_data_in[61] ^ enc_data_in[63];

    // cb[1]: covers positions where bit 1 is set
    assign enc_check_out[1] =
        enc_data_in[0]  ^ enc_data_in[2]  ^ enc_data_in[3]  ^ enc_data_in[5]  ^
        enc_data_in[6]  ^ enc_data_in[9]  ^ enc_data_in[10] ^ enc_data_in[12] ^
        enc_data_in[13] ^ enc_data_in[16] ^ enc_data_in[17] ^ enc_data_in[20] ^
        enc_data_in[21] ^ enc_data_in[24] ^ enc_data_in[25] ^ enc_data_in[27] ^
        enc_data_in[28] ^ enc_data_in[31] ^ enc_data_in[32] ^ enc_data_in[35] ^
        enc_data_in[36] ^ enc_data_in[39] ^ enc_data_in[40] ^ enc_data_in[43] ^
        enc_data_in[44] ^ enc_data_in[47] ^ enc_data_in[48] ^ enc_data_in[51] ^
        enc_data_in[52] ^ enc_data_in[55] ^ enc_data_in[56] ^ enc_data_in[58] ^
        enc_data_in[59] ^ enc_data_in[62] ^ enc_data_in[63];

    // cb[2]: covers positions where bit 2 is set
    assign enc_check_out[2] =
        enc_data_in[1]  ^ enc_data_in[2]  ^ enc_data_in[3]  ^ enc_data_in[7]  ^
        enc_data_in[8]  ^ enc_data_in[9]  ^ enc_data_in[10] ^ enc_data_in[14] ^
        enc_data_in[15] ^ enc_data_in[16] ^ enc_data_in[17] ^ enc_data_in[22] ^
        enc_data_in[23] ^ enc_data_in[24] ^ enc_data_in[25] ^ enc_data_in[29] ^
        enc_data_in[30] ^ enc_data_in[31] ^ enc_data_in[32] ^ enc_data_in[37] ^
        enc_data_in[38] ^ enc_data_in[39] ^ enc_data_in[40] ^ enc_data_in[45] ^
        enc_data_in[46] ^ enc_data_in[47] ^ enc_data_in[48] ^ enc_data_in[53] ^
        enc_data_in[54] ^ enc_data_in[55] ^ enc_data_in[56] ^ enc_data_in[60] ^
        enc_data_in[61] ^ enc_data_in[62] ^ enc_data_in[63];

    // cb[3]: covers positions where bit 3 is set (ranges 9-15, 24-31, 40-47, 56-63)
    assign enc_check_out[3] =
        enc_data_in[4]  ^ enc_data_in[5]  ^ enc_data_in[6]  ^ enc_data_in[7]  ^
        enc_data_in[8]  ^ enc_data_in[9]  ^ enc_data_in[10] ^ enc_data_in[18] ^
        enc_data_in[19] ^ enc_data_in[20] ^ enc_data_in[21] ^ enc_data_in[22] ^
        enc_data_in[23] ^ enc_data_in[24] ^ enc_data_in[25] ^ enc_data_in[33] ^
        enc_data_in[34] ^ enc_data_in[35] ^ enc_data_in[36] ^ enc_data_in[37] ^
        enc_data_in[38] ^ enc_data_in[39] ^ enc_data_in[40] ^ enc_data_in[49] ^
        enc_data_in[50] ^ enc_data_in[51] ^ enc_data_in[52] ^ enc_data_in[53] ^
        enc_data_in[54] ^ enc_data_in[55] ^ enc_data_in[56];

    // cb[4]: covers positions where bit 4 is set (ranges 17-31, 48-63)
    assign enc_check_out[4] =
        enc_data_in[11] ^ enc_data_in[12] ^ enc_data_in[13] ^ enc_data_in[14] ^
        enc_data_in[15] ^ enc_data_in[16] ^ enc_data_in[17] ^ enc_data_in[18] ^
        enc_data_in[19] ^ enc_data_in[20] ^ enc_data_in[21] ^ enc_data_in[22] ^
        enc_data_in[23] ^ enc_data_in[24] ^ enc_data_in[25] ^ enc_data_in[41] ^
        enc_data_in[42] ^ enc_data_in[43] ^ enc_data_in[44] ^ enc_data_in[45] ^
        enc_data_in[46] ^ enc_data_in[47] ^ enc_data_in[48] ^ enc_data_in[49] ^
        enc_data_in[50] ^ enc_data_in[51] ^ enc_data_in[52] ^ enc_data_in[53] ^
        enc_data_in[54] ^ enc_data_in[55] ^ enc_data_in[56];

    // cb[5]: covers positions where bit 5 is set (range 33-63)
    assign enc_check_out[5] =
        enc_data_in[26] ^ enc_data_in[27] ^ enc_data_in[28] ^ enc_data_in[29] ^
        enc_data_in[30] ^ enc_data_in[31] ^ enc_data_in[32] ^ enc_data_in[33] ^
        enc_data_in[34] ^ enc_data_in[35] ^ enc_data_in[36] ^ enc_data_in[37] ^
        enc_data_in[38] ^ enc_data_in[39] ^ enc_data_in[40] ^ enc_data_in[41] ^
        enc_data_in[42] ^ enc_data_in[43] ^ enc_data_in[44] ^ enc_data_in[45] ^
        enc_data_in[46] ^ enc_data_in[47] ^ enc_data_in[48] ^ enc_data_in[49] ^
        enc_data_in[50] ^ enc_data_in[51] ^ enc_data_in[52] ^ enc_data_in[53] ^
        enc_data_in[54] ^ enc_data_in[55] ^ enc_data_in[56];

    // cb[6]: covers positions where bit 6 is set (range 65-71 = d[57..63])
    assign enc_check_out[6] =
        enc_data_in[57] ^ enc_data_in[58] ^ enc_data_in[59] ^ enc_data_in[60] ^
        enc_data_in[61] ^ enc_data_in[62] ^ enc_data_in[63];

    // cb[7]: overall parity over all 71 bits (data + cb[6:0])
    assign enc_check_out[7] = ^enc_data_in ^ ^enc_check_out[6:0];

    // Output word: {check_bits[7:0], data[63:0]}
    assign enc_word_out = {enc_check_out, enc_data_in};

endmodule

`default_nettype wire

tb/ecc_encoder_tb.v
// ecc_encoder_tb.v – Testbench for ecc_encoder (SECDED 72,64)
//
// Tests:
//   1. d=0 produces all-zero check bits
//   2. Known test vectors (Python-verified reference values)
//   3. All 64 single-bit data patterns: round-trip via inline
//      reference model; verify enc_word_out = {enc_check_out, enc_data_in}
//   4. Structural check: enc_word_out[63:0] always equals enc_data_in
//
// Compile & run:
//   iverilog -g2012 -o build/ecc_encoder.out tb/ecc_encoder_tb.v rtl/ecc_encoder.v
//   vvp build/ecc_encoder.out

`timescale 1ns/1ps

module ecc_encoder_tb;

    // ----------------------------------------------------------------
    // DUT wires
    // ----------------------------------------------------------------
    reg  [63:0] enc_data_in;
    wire [7:0]  enc_check_out;
    wire [71:0] enc_word_out;

    ecc_encoder dut (
        .enc_data_in  (enc_data_in),
        .enc_check_out(enc_check_out),
        .enc_word_out (enc_word_out)
    );

    // ----------------------------------------------------------------
    // VCD / waveform dump
    // ----------------------------------------------------------------
    initial begin
        $dumpfile("results/phase-ddr4-ecc/ecc_encoder.vcd");
        $dumpvars(0, ecc_encoder_tb);
    end

    // ----------------------------------------------------------------
    // Reference model (pure Verilog, mirrors Python-verified logic)
    // Bit positions of d[0..63] in the logical Hamming codeword:
    //   d[0..3]  -> 3,5,6,7   d[4..10] -> 9..15
    //   d[11..25]-> 17..31    d[26..56]-> 33..63
    //   d[57..63]-> 65..71
    // cb[k] = even parity of data bits whose position has bit k set.
    // cb[7] = overall parity of all 71 bits.
    // ----------------------------------------------------------------
    function [7:0] ref_check_bits;
        input [63:0] d;
        reg [6:0] c;
        begin
            c[0] = d[0]^d[1]^d[3]^d[4]^d[6]^d[8]^d[10]^d[11]^d[13]^d[15]^
                   d[17]^d[19]^d[21]^d[23]^d[25]^d[26]^d[28]^d[30]^d[32]^d[34]^
                   d[36]^d[38]^d[40]^d[42]^d[44]^d[46]^d[48]^d[50]^d[52]^d[54]^
                   d[56]^d[57]^d[59]^d[61]^d[63];
            c[1] = d[0]^d[2]^d[3]^d[5]^d[6]^d[9]^d[10]^d[12]^d[13]^d[16]^
                   d[17]^d[20]^d[21]^d[24]^d[25]^d[27]^d[28]^d[31]^d[32]^d[35]^
                   d[36]^d[39]^d[40]^d[43]^d[44]^d[47]^d[48]^d[51]^d[52]^d[55]^
                   d[56]^d[58]^d[59]^d[62]^d[63];
            c[2] = d[1]^d[2]^d[3]^d[7]^d[8]^d[9]^d[10]^d[14]^d[15]^d[16]^
                   d[17]^d[22]^d[23]^d[24]^d[25]^d[29]^d[30]^d[31]^d[32]^d[37]^
                   d[38]^d[39]^d[40]^d[45]^d[46]^d[47]^d[48]^d[53]^d[54]^d[55]^
                   d[56]^d[60]^d[61]^d[62]^d[63];
            c[3] = d[4]^d[5]^d[6]^d[7]^d[8]^d[9]^d[10]^d[18]^d[19]^d[20]^
                   d[21]^d[22]^d[23]^d[24]^d[25]^d[33]^d[34]^d[35]^d[36]^d[37]^
                   d[38]^d[39]^d[40]^d[49]^d[50]^d[51]^d[52]^d[53]^d[54]^d[55]^
                   d[56];
            c[4] = d[11]^d[12]^d[13]^d[14]^d[15]^d[16]^d[17]^d[18]^d[19]^
                   d[20]^d[21]^d[22]^d[23]^d[24]^d[25]^d[41]^d[42]^d[43]^d[44]^
                   d[45]^d[46]^d[47]^d[48]^d[49]^d[50]^d[51]^d[52]^d[53]^d[54]^
                   d[55]^d[56];
            c[5] = d[26]^d[27]^d[28]^d[29]^d[30]^d[31]^d[32]^d[33]^d[34]^
                   d[35]^d[36]^d[37]^d[38]^d[39]^d[40]^d[41]^d[42]^d[43]^d[44]^
                   d[45]^d[46]^d[47]^d[48]^d[49]^d[50]^d[51]^d[52]^d[53]^d[54]^
                   d[55]^d[56];
            c[6] = d[57]^d[58]^d[59]^d[60]^d[61]^d[62]^d[63];
            ref_check_bits = {(^d ^ ^c), c};
        end
    endfunction

    // ----------------------------------------------------------------
    // Test sequencer
    // ----------------------------------------------------------------
    integer i;
    integer pass_count, fail_count;
    reg [7:0] expected_cb;

    initial begin
        pass_count = 0;
        fail_count = 0;

        // ---- Test 1: d=0 -------------------------------------------
        enc_data_in = 64'h0;
        #1;
        if (enc_check_out !== 8'h00) begin
            $display("FAIL T1: d=0 expected cb=8'h00, got 8'h%02x", enc_check_out);
            fail_count = fail_count + 1;
        end else begin
            $display("PASS T1: d=0 => cb=8'h00");
            pass_count = pass_count + 1;
        end

        // ---- Test 2: d=all-ones ------------------------------------
        enc_data_in = 64'hFFFFFFFFFFFFFFFF;
        #1;
        if (enc_check_out !== 8'hFF) begin
            $display("FAIL T2: d=all1s expected cb=8'hFF, got 8'h%02x", enc_check_out);
            fail_count = fail_count + 1;
        end else begin
            $display("PASS T2: d=all1s => cb=8'hFF");
            pass_count = pass_count + 1;
        end

        // ---- Test 3: Known vectors (Python-verified) ---------------
        enc_data_in = 64'hDEADBEEFCAFEBABE; #1;
        if (enc_check_out !== 8'h3A) begin
            $display("FAIL T3a: d=DEADBEEF.. expected 8'h3a got 8'h%02x", enc_check_out);
            fail_count = fail_count + 1;
        end else begin
            $display("PASS T3a: d=0xDEADBEEFCAFEBABE cb=0x3a");
            pass_count = pass_count + 1;
        end

        enc_data_in = 64'h0000000000000001; #1;
        if (enc_check_out !== 8'h83) begin
            $display("FAIL T3b: d=1 expected 8'h83 got 8'h%02x", enc_check_out);
            fail_count = fail_count + 1;
        end else begin
            $display("PASS T3b: d=0x0000000000000001 cb=0x83");
            pass_count = pass_count + 1;
        end

        enc_data_in = 64'h8000000000000000; #1;
        if (enc_check_out !== 8'hC7) begin
            $display("FAIL T3c: d=MSB expected 8'hC7 got 8'h%02x", enc_check_out);
            fail_count = fail_count + 1;
        end else begin
            $display("PASS T3c: d=0x8000000000000000 cb=0xc7");
            pass_count = pass_count + 1;
        end

        // ---- Test 4: enc_word_out structure -------------------------
        enc_data_in = 64'h5A5A5A5A5A5A5A5A; #1;
        if (enc_word_out[63:0] !== enc_data_in) begin
            $display("FAIL T4: enc_word_out[63:0] != enc_data_in");
            fail_count = fail_count + 1;
        end else if (enc_word_out[71:64] !== enc_check_out) begin
            $display("FAIL T4: enc_word_out[71:64] != enc_check_out");
            fail_count = fail_count + 1;
        end else begin
            $display("PASS T4: enc_word_out = {enc_check_out, enc_data_in}");
            pass_count = pass_count + 1;
        end

        // ---- Test 5: All 64 single-bit patterns --------------------
        $display("Running 64 single-bit data pattern checks...");
        for (i = 0; i < 64; i = i + 1) begin
            enc_data_in = 64'h1 << i;
            #1;
            expected_cb = ref_check_bits(enc_data_in);
            if (enc_check_out !== expected_cb) begin
                $display("FAIL T5 d[%0d]=1: expected cb=8'h%02x got 8'h%02x",
                         i, expected_cb, enc_check_out);
                fail_count = fail_count + 1;
            end else begin
                pass_count = pass_count + 1;
            end
        end
        $display("PASS T5: all 64 single-bit patterns match reference model");

        // ---- Test 6: Parity balance for d=all-zeros ----------------
        enc_data_in = 64'h0; #1;
        if ((^enc_word_out) !== 1'b0) begin
            $display("FAIL T6: overall parity of encoded all-zero word is not 0");
            fail_count = fail_count + 1;
        end else begin
            $display("PASS T6: overall parity of encoded all-zero word is 0");
            pass_count = pass_count + 1;
        end

        // ---- Test 7: Alternating patterns --------------------------
        enc_data_in = 64'h5555555555555555; #1;
        expected_cb = ref_check_bits(enc_data_in);
        if (enc_check_out !== expected_cb) begin
            $display("FAIL T7a: d=0x5555... cb mismatch");
            fail_count = fail_count + 1;
        end else begin
            $display("PASS T7a: d=0x5555555555555555 cb=8'h%02x", enc_check_out);
            pass_count = pass_count + 1;
        end

        enc_data_in = 64'hAAAAAAAAAAAAAAAA; #1;
        expected_cb = ref_check_bits(enc_data_in);
        if (enc_check_out !== expected_cb) begin
            $display("FAIL T7b: d=0xAAAA... cb mismatch");
            fail_count = fail_count + 1;
        end else begin
            $display("PASS T7b: d=0xAAAAAAAAAAAAAAAA cb=8'h%02x", enc_check_out);
            pass_count = pass_count + 1;
        end

        // ---- Summary -----------------------------------------------
        $display("--------------------------------------------");
        $display("ecc_encoder_tb: %0d PASSED, %0d FAILED", pass_count, fail_count);
        $display("--------------------------------------------");
        if (fail_count != 0) $fatal(1, "ecc_encoder_tb: simulation FAILED");
        $finish;
    end

endmodule

results/phase-ddr4-ecc/ecc_encoder.vcd
$date
	Thu Mar 12 09:46:30 2026
$end
$version
	Icarus Verilog
$end
$timescale
	1ps
$end
$scope module ecc_encoder_tb $end
$var wire 72 ! enc_word_out [71:0] $end
$var wire 8 " enc_check_out [7:0] $end
$var reg 64 # enc_data_in [63:0] $end
$var reg 8 $ expected_cb [7:0] $end
$var integer 32 % fail_count [31:0] $end
$var integer 32 & i [31:0] $end
$var integer 32 ' pass_count [31:0] $end
$scope function ref_check_bits $end
$var reg 7 ( c [6:0] $end
$var reg 64 ) d [63:0] $end
$upscope $end
$scope module dut $end
$var wire 64 * enc_data_in [63:0] $end
$var wire 72 + enc_word_out [71:0] $end
$var wire 8 , enc_check_out [7:0] $end
$upscope $end
$upscope $end
$enddefinitions $end
$comment Show the parameter values. $end
$dumpall
$end
#0
$dumpvars
b0 ,
b0 +
b0 *
bx )
bx (
b0 '
bx &
b0 %
bx $
b0 #
b0 "
b0 !
$end
#1000
b11111111 "
b11111111 ,
b111111111111111111111111111111111111111111111111111111111111111111111111 !
b111111111111111111111111111111111111111111111111111111111111111111111111 +
b1111111111111111111111111111111111111111111111111111111111111111 #
b1111111111111111111111111111111111111111111111111111111111111111 *
b1 '
#2000
b111010 "
b111010 ,
b1110101101111010101101101111101110111111001010111111101011101010111110 !
b1110101101111010101101101111101110111111001010111111101011101010111110 +
b1101111010101101101111101110111111001010111111101011101010111110 #
b1101111010101101101111101110111111001010111111101011101010111110 *
b10 '
#3000
b10000011 "
b10000011 ,
b100000110000000000000000000000000000000000000000000000000000000000000001 !
b100000110000000000000000000000000000000000000000000000000000000000000001 +
b1 #
b1 *
b11 '
#4000
b11000111 "
b11000111 ,
b110001111000000000000000000000000000000000000000000000000000000000000000 !
b110001111000000000000000000000000000000000000000000000000000000000000000 +
b1000000000000000000000000000000000000000000000000000000000000000 #
b1000000000000000000000000000000000000000000000000000000000000000 *
b100 '
#5000
b101110 "
b101110 ,
b1011100101101001011010010110100101101001011010010110100101101001011010 !
b1011100101101001011010010110100101101001011010010110100101101001011010 +
b101101001011010010110100101101001011010010110100101101001011010 #
b101101001011010010110100101101001011010010110100101101001011010 *
b101 '
#6000
b10000011 "
b10000011 ,
b100000110000000000000000000000000000000000000000000000000000000000000001 !
b100000110000000000000000000000000000000000000000000000000000000000000001 +
b1 #
b1 *
b0 &
b110 '
#7000
b10000101 "
b10000101 ,
b100001010000000000000000000000000000000000000000000000000000000000000010 !
b100001010000000000000000000000000000000000000000000000000000000000000010 +
b10 #
b10 *
b1 &
b111 '
b10000011 $
b11 (
b1 )
#8000
b10000110 "
b10000110 ,
b100001100000000000000000000000000000000000000000000000000000000000000100 !
b100001100000000000000000000000000000000000000000000000000000000000000100 +
b100 #
b100 *
b10 &
b1000 '
b10000101 $
b101 (
b10 )
#9000
b111 "
b111 ,
b1110000000000000000000000000000000000000000000000000000000000001000 !
b1110000000000000000000000000000000000000000000000000000000000001000 +
b1000 #
b1000 *
b11 &
b1001 '
b10000110 $
b110 (
b100 )
#10000
b10001001 "
b10001001 ,
b100010010000000000000000000000000000000000000000000000000000000000010000 !
b100010010000000000000000000000000000000000000000000000000000000000010000 +
b10000 #
b10000 *
b100 &
b1010 '
b111 $
b111 (
b1000 )
#11000
b10001010 "
b10001010 ,
b100010100000000000000000000000000000000000000000000000000000000000100000 !
b100010100000000000000000000000000000000000000000000000000000000000100000 +
b100000 #
b100000 *
b101 &
b1011 '
b10001001 $
b1001 (
b10000 )
#12000
b1011 "
b1011 ,
b10110000000000000000000000000000000000000000000000000000000001000000 !
b10110000000000000000000000000000000000000000000000000000000001000000 +
b1000000 #
b1000000 *
b110 &
b1100 '
b10001010 $
b1010 (
b100000 )
#13000
b10001100 "
b10001100 ,
b100011000000000000000000000000000000000000000000000000000000000010000000 !
b100011000000000000000000000000000000000000000000000000000000000010000000 +
b10000000 #
b10000000 *
b111 &
b1101 '
b1011 $
b1011 (
b1000000 )
#14000
b1101 "
b1101 ,
b11010000000000000000000000000000000000000000000000000000000100000000 !
b11010000000000000000000000000000000000000000000000000000000100000000 +
b100000000 #
b100000000 *
b1000 &
b1110 '
b10001100 $
b1100 (
b10000000 )
#15000
b1110 "
b1110 ,
b11100000000000000000000000000000000000000000000000000000001000000000 !
b11100000000000000000000000000000000000000000000000000000001000000000 +
b1000000000 #
b1000000000 *
b1001 &
b1111 '
b1101 $
b1101 (
b100000000 )
#16000
b10001111 "
b10001111 ,
b100011110000000000000000000000000000000000000000000000000000010000000000 !
b100011110000000000000000000000000000000000000000000000000000010000000000 +
b10000000000 #
b10000000000 *
b1010 &
b10000 '
b1110 $
b1110 (
b1000000000 )
#17000
b10010001 "
b10010001 ,
b100100010000000000000000000000000000000000000000000000000000100000000000 !
b100100010000000000000000000000000000000000000000000000000000100000000000 +
b100000000000 #
b100000000000 *
b1011 &
b10001 '
b10001111 $
b1111 (
b10000000000 )
#18000
b10010010 "
b10010010 ,
b100100100000000000000000000000000000000000000000000000000001000000000000 !
b100100100000000000000000000000000000000000000000000000000001000000000000 +
b1000000000000 #
b1000000000000 *
b1100 &
b10010 '
b10010001 $
b10001 (
b100000000000 )
#19000
b10011 "
b10011 ,
b100110000000000000000000000000000000000000000000000000010000000000000 !
b100110000000000000000000000000000000000000000000000000010000000000000 +
b10000000000000 #
b10000000000000 *
b1101 &
b10011 '
b10010010 $
b10010 (
b1000000000000 )
#20000
b10010100 "
b10010100 ,
b100101000000000000000000000000000000000000000000000000000100000000000000 !
b100101000000000000000000000000000000000000000000000000000100000000000000 +
b100000000000000 #
b100000000000000 *
b1110 &
b10100 '
b10011 $
b10011 (
b10000000000000 )
#21000
b10101 "
b10101 ,
b101010000000000000000000000000000000000000000000000001000000000000000 !
b101010000000000000000000000000000000000000000000000001000000000000000 +
b1000000000000000 #
b1000000000000000 *
b1111 &
b10101 '
b10010100 $
b10100 (
b100000000000000 )
#22000
b10110 "
b10110 ,
b101100000000000000000000000000000000000000000000000010000000000000000 !
b101100000000000000000000000000000000000000000000000010000000000000000 +
b10000000000000000 #
b10000000000000000 *
b10000 &
b10110 '
b10101 $
b10101 (
b1000000000000000 )
#23000
b10010111 "
b10010111 ,
b100101110000000000000000000000000000000000000000000000100000000000000000 !
b100101110000000000000000000000000000000000000000000000100000000000000000 +
b100000000000000000 #
b100000000000000000 *
b10001 &
b10111 '
b10110 $
b10110 (
b10000000000000000 )
#24000
b10011000 "
b10011000 ,
b100110000000000000000000000000000000000000000000000001000000000000000000 !
b100110000000000000000000000000000000000000000000000001000000000000000000 +
b1000000000000000000 #
b1000000000000000000 *
b10010 &
b11000 '
b10010111 $
b10111 (
b100000000000000000 )
#25000
b11001 "
b11001 ,
b110010000000000000000000000000000000000000000000010000000000000000000 !
b110010000000000000000000000000000000000000000000010000000000000000000 +
b10000000000000000000 #
b10000000000000000000 *
b10011 &
b11001 '
b10011000 $
b11000 (
b1000000000000000000 )
#26000
b11010 "
b11010 ,
b110100000000000000000000000000000000000000000000100000000000000000000 !
b110100000000000000000000000000000000000000000000100000000000000000000 +
b100000000000000000000 #
b100000000000000000000 *
b10100 &
b11010 '
b11001 $
b11001 (
b10000000000000000000 )
#27000
b10011011 "
b10011011 ,
b100110110000000000000000000000000000000000000000001000000000000000000000 !
b100110110000000000000000000000000000000000000000001000000000000000000000 +
b1000000000000000000000 #
b1000000000000000000000 *
b10101 &
b11011 '
b11010 $
b11010 (
b100000000000000000000 )
#28000
b11100 "
b11100 ,
b111000000000000000000000000000000000000000000010000000000000000000000 !
b111000000000000000000000000000000000000000000010000000000000000000000 +
b10000000000000000000000 #
b10000000000000000000000 *
b10110 &
b11100 '
b10011011 $
b11011 (
b1000000000000000000000 )
#29000
b10011101 "
b10011101 ,
b100111010000000000000000000000000000000000000000100000000000000000000000 !
b100111010000000000000000000000000000000000000000100000000000000000000000 +
b100000000000000000000000 #
b100000000000000000000000 *
b10111 &
b11101 '
b11100 $
b11100 (
b10000000000000000000000 )
#30000
b10011110 "
b10011110 ,
b100111100000000000000000000000000000000000000001000000000000000000000000 !
b100111100000000000000000000000000000000000000001000000000000000000000000 +
b1000000000000000000000000 #
b1000000000000000000000000 *
b11000 &
b11110 '
b10011101 $
b11101 (
b100000000000000000000000 )
#31000
b11111 "
b11111 ,
b111110000000000000000000000000000000000000010000000000000000000000000 !
b111110000000000000000000000000000000000000010000000000000000000000000 +
b10000000000000000000000000 #
b10000000000000000000000000 *
b11001 &
b11111 '
b10011110 $
b11110 (
b1000000000000000000000000 )
#32000
b10100001 "
b10100001 ,
b101000010000000000000000000000000000000000000100000000000000000000000000 !
b101000010000000000000000000000000000000000000100000000000000000000000000 +
b100000000000000000000000000 #
b100000000000000000000000000 *
b11010 &
b100000 '
b11111 $
b11111 (
b10000000000000000000000000 )
#33000
b10100010 "
b10100010 ,
b101000100000000000000000000000000000000000001000000000000000000000000000 !
b101000100000000000000000000000000000000000001000000000000000000000000000 +
b1000000000000000000000000000 #
b1000000000000000000000000000 *
b11011 &
b100001 '
b10100001 $
b100001 (
b100000000000000000000000000 )
#34000
b100011 "
b100011 ,
b1000110000000000000000000000000000000000010000000000000000000000000000 !
b1000110000000000000000000000000000000000010000000000000000000000000000 +
b10000000000000000000000000000 #
b10000000000000000000000000000 *
b11100 &
b100010 '
b10100010 $
b100010 (
b1000000000000000000000000000 )
#35000
b10100100 "
b10100100 ,
b101001000000000000000000000000000000000000100000000000000000000000000000 !
b101001000000000000000000000000000000000000100000000000000000000000000000 +
b100000000000000000000000000000 #
b100000000000000000000000000000 *
b11101 &
b100011 '
b100011 $
b100011 (
b10000000000000000000000000000 )
#36000
b100101 "
b100101 ,
b1001010000000000000000000000000000000001000000000000000000000000000000 !
b1001010000000000000000000000000000000001000000000000000000000000000000 +
b1000000000000000000000000000000 #
b1000000000000000000000000000000 *
b11110 &
b100100 '
b10100100 $
b100100 (
b100000000000000000000000000000 )
#37000
b100110 "
b100110 ,
b1001100000000000000000000000000000000010000000000000000000000000000000 !
b1001100000000000000000000000000000000010000000000000000000000000000000 +
b10000000000000000000000000000000 #
b10000000000000000000000000000000 *
b11111 &
b100101 '
b100101 $
b100101 (
b1000000000000000000000000000000 )
#38000
b10100111 "
b10100111 ,
b101001110000000000000000000000000000000100000000000000000000000000000000 !
b101001110000000000000000000000000000000100000000000000000000000000000000 +
b100000000000000000000000000000000 #
b100000000000000000000000000000000 *
b100000 &
b100110 '
b100110 $
b100110 (
b10000000000000000000000000000000 )
#39000
b10101000 "
b10101000 ,
b101010000000000000000000000000000000001000000000000000000000000000000000 !
b101010000000000000000000000000000000001000000000000000000000000000000000 +
b1000000000000000000000000000000000 #
b1000000000000000000000000000000000 *
b100001 &
b100111 '
b10100111 $
b100111 (
b100000000000000000000000000000000 )
#40000
b101001 "
b101001 ,
b1010010000000000000000000000000000010000000000000000000000000000000000 !
b1010010000000000000000000000000000010000000000000000000000000000000000 +
b10000000000000000000000000000000000 #
b10000000000000000000000000000000000 *
b100010 &
b101000 '
b10101000 $
b101000 (
b1000000000000000000000000000000000 )
#41000
b101010 "
b101010 ,
b1010100000000000000000000000000000100000000000000000000000000000000000 !
b1010100000000000000000000000000000100000000000000000000000000000000000 +
b100000000000000000000000000000000000 #
b100000000000000000000000000000000000 *
b100011 &
b101001 '
b101001 $
b101001 (
b10000000000000000000000000000000000 )
#42000
b10101011 "
b10101011 ,
b101010110000000000000000000000000001000000000000000000000000000000000000 !
b101010110000000000000000000000000001000000000000000000000000000000000000 +
b1000000000000000000000000000000000000 #
b1000000000000000000000000000000000000 *
b100100 &
b101010 '
b101010 $
b101010 (
b100000000000000000000000000000000000 )
#43000
b101100 "
b101100 ,
b1011000000000000000000000000000010000000000000000000000000000000000000 !
b1011000000000000000000000000000010000000000000000000000000000000000000 +
b10000000000000000000000000000000000000 #
b10000000000000000000000000000000000000 *
b100101 &
b101011 '
b10101011 $
b101011 (
b1000000000000000000000000000000000000 )
#44000
b10101101 "
b10101101 ,
b101011010000000000000000000000000100000000000000000000000000000000000000 !
b101011010000000000000000000000000100000000000000000000000000000000000000 +
b100000000000000000000000000000000000000 #
b100000000000000000000000000000000000000 *
b100110 &
b101100 '
b101100 $
b101100 (
b10000000000000000000000000000000000000 )
#45000
b10101110 "
b10101110 ,
b101011100000000000000000000000001000000000000000000000000000000000000000 !
b101011100000000000000000000000001000000000000000000000000000000000000000 +
b1000000000000000000000000000000000000000 #
b1000000000000000000000000000000000000000 *
b100111 &
b101101 '
b10101101 $
b101101 (
b100000000000000000000000000000000000000 )
#46000
b101111 "
b101111 ,
b1011110000000000000000000000010000000000000000000000000000000000000000 !
b1011110000000000000000000000010000000000000000000000000000000000000000 +
b10000000000000000000000000000000000000000 #
b10000000000000000000000000000000000000000 *
b101000 &
b101110 '
b10101110 $
b101110 (
b1000000000000000000000000000000000000000 )
#47000
b10110000 "
b10110000 ,
b101100000000000000000000000000100000000000000000000000000000000000000000 !
b101100000000000000000000000000100000000000000000000000000000000000000000 +
b100000000000000000000000000000000000000000 #
b100000000000000000000000000000000000000000 *
b101001 &
b101111 '
b101111 $
b101111 (
b10000000000000000000000000000000000000000 )
#48000
b110001 "
b110001 ,
b1100010000000000000000000001000000000000000000000000000000000000000000 !
b1100010000000000000000000001000000000000000000000000000000000000000000 +
b1000000000000000000000000000000000000000000 #
b1000000000000000000000000000000000000000000 *
b101010 &
b110000 '
b10110000 $
b110000 (
b100000000000000000000000000000000000000000 )
#49000
b110010 "
b110010 ,
b1100100000000000000000000010000000000000000000000000000000000000000000 !
b1100100000000000000000000010000000000000000000000000000000000000000000 +
b10000000000000000000000000000000000000000000 #
b10000000000000000000000000000000000000000000 *
b101011 &
b110001 '
b110001 $
b110001 (
b1000000000000000000000000000000000000000000 )
#50000
b10110011 "
b10110011 ,
b101100110000000000000000000100000000000000000000000000000000000000000000 !
b101100110000000000000000000100000000000000000000000000000000000000000000 +
b100000000000000000000000000000000000000000000 #
b100000000000000000000000000000000000000000000 *
b101100 &
b110010 '
b110010 $
b110010 (
b10000000000000000000000000000000000000000000 )
#51000
b110100 "
b110100 ,
b1101000000000000000000001000000000000000000000000000000000000000000000 !
b1101000000000000000000001000000000000000000000000000000000000000000000 +
b1000000000000000000000000000000000000000000000 #
b1000000000000000000000000000000000000000000000 *
b101101 &
b110011 '
b10110011 $
b110011 (
b100000000000000000000000000000000000000000000 )
