rtl/refresh_ctrl.v
// refresh_ctrl.v – DDR4 Refresh Controller
//
// Implements the three-state refresh FSM from docs/ARCHITECTURE.md §6.2:
//   NORMAL -> REF_PENDING -> REFRESHING -> NORMAL
//
// Supports two refresh modes (selected by rfsh_mode):
//   0 = All-Bank Refresh (REFab): one REF to all banks every tREFI.
//       All banks must be idle before the REF issues; all stall for tRFC.
//   1 = Per-Bank Refresh (REFpb): one bank refreshed per tREFI interval,
//       cycling through all BANK_GROUPS × BANKS_PER_GROUP banks in order.
//       Other banks may remain active while the target bank refreshes.
//
// Temperature-compensated refresh: temp_throttle=1 halves the effective
// tREFI (per JEDEC DDR4 >85 °C requirement).
//
// Interface outputs:
//   ref_req       – asserted in REF_PENDING; arbiter should stop new ACTs
//   ref_issue     – single-cycle pulse when REF command should be issued
//   ref_stall     – asserted during REFRESHING (tRFC countdown active)
//   ref_bank      – target bank  for REFpb (valid when rfsh_mode=1)
//   ref_bank_group– target group for REFpb (valid when rfsh_mode=1)
//   ref_active    – 1 whenever not in NORMAL (refresh cycle in progress)
//
// Interface inputs:
//   all_banks_idle – from bank FSMs: all banks are precharged
//   rfsh_mode      – 0=REFab, 1=REFpb
//   temp_throttle  – 1=high temperature, halve tREFI
//
// Reset: active-low synchronous (posedge clk).
//
// Compile & run:
//   iverilog -g2012 -o build/refresh_ctrl.out tb/refresh_ctrl_tb.v rtl/refresh_ctrl.v
//   vvp build/refresh_ctrl.out

`default_nettype none

module refresh_ctrl #(
    parameter BANK_GROUPS      = 4,
    parameter BANKS_PER_GROUP  = 4,
    // Timing parameters in clock cycles (DDR4-3200, 625 ps tCK defaults)
    parameter P_TREFI          = 12480, // tREFI  7800 ns / 0.625 ns
    parameter P_TRFC           = 560    // tRFC1  350 ns  / 0.625 ns (8 Gb)
)(
    input  wire clk,
    input  wire rst_n,

    // Scheduler / bank interface
    input  wire all_banks_idle, // all banks are in IDLE (precharged)
    input  wire rfsh_mode,      // 0 = REFab, 1 = REFpb
    input  wire temp_throttle,  // 1 = >85 °C; halve tREFI

    // Outputs to arbiter / command bus
    output reg  ref_req,        // 1 while waiting for banks to drain
    output reg  ref_issue,      // 1-cycle pulse: issue REF to DRAM now
    output reg  ref_stall,      // 1 during tRFC countdown (block all cmds)
    output reg  ref_active,     // 1 whenever not in NORMAL

    // REFpb target (valid when rfsh_mode=1 and ref_issue=1)
    output reg  [1:0] ref_bank_group,
    output reg  [1:0] ref_bank
);

    // ---------------------------------------------------------------
    // Derived constants
    // ---------------------------------------------------------------
    localparam TOTAL_BANKS = BANK_GROUPS * BANKS_PER_GROUP;

    // Counter widths – sized to hold worst-case values
    localparam TREFI_W = 14;  // 2^14 = 16384 > 12480
    localparam TRFC_W  = 10;  // 2^10 = 1024  > 560
    localparam BANK_W  = 4;   // up to 16 banks total

    // ---------------------------------------------------------------
    // State encodings
    // ---------------------------------------------------------------
    localparam S_NORMAL      = 2'd0;
    localparam S_REF_PENDING = 2'd1;
    localparam S_REFRESHING  = 2'd2;

    // ---------------------------------------------------------------
    // Registers
    // ---------------------------------------------------------------
    reg [1:0]        state;
    reg [TREFI_W-1:0] trefi_cnt;   // counts down from P_TREFI-1 to 0
    reg [TRFC_W-1:0]  trfc_cnt;    // counts down during REFRESHING
    reg [BANK_W-1:0]  bank_idx;    // current bank index for REFpb

    // Effective tREFI: halved when temp_throttle is asserted
    wire [TREFI_W-1:0] trefi_val;
    assign trefi_val = temp_throttle ?
                       ((P_TREFI >> 1) - 1) :
                       (P_TREFI - 1);

    // ---------------------------------------------------------------
    // Condition to start a refresh (bank must be idle for REFpb target
    // or all banks must be idle for REFab)
    // ---------------------------------------------------------------
    // For REFab: all_banks_idle must be high.
    // For REFpb: only the target bank needs to be idle; since we do not
    //            have per-bank idle signals in this standalone module we
    //            use all_banks_idle as a conservative approximation
    //            (integrator can replace this with a per-bank signal).
    wire can_refresh;
    assign can_refresh = all_banks_idle;

    // Separate bank index bits: group = idx / BANKS_PER_GROUP,
    //                            bank  = idx % BANKS_PER_GROUP
    // Uses integer division – valid because BANKS_PER_GROUP is a power of 2.
    wire [1:0] bank_idx_group;
    wire [1:0] bank_idx_bank;
    assign bank_idx_group = bank_idx / BANKS_PER_GROUP;
    assign bank_idx_bank  = bank_idx % BANKS_PER_GROUP;

    // ---------------------------------------------------------------
    // Sequential FSM
    // ---------------------------------------------------------------
    always @(posedge clk) begin
        if (!rst_n) begin
            state          <= S_NORMAL;
            trefi_cnt      <= P_TREFI - 1;
            trfc_cnt       <= {TRFC_W{1'b0}};
            bank_idx       <= {BANK_W{1'b0}};
            ref_req        <= 1'b0;
            ref_issue      <= 1'b0;
            ref_stall      <= 1'b0;
            ref_active     <= 1'b0;
            ref_bank_group <= 2'd0;
            ref_bank       <= 2'd0;
        end else begin
            // Default: clear single-cycle pulse
            ref_issue <= 1'b0;

            case (state)

                // ---- NORMAL: counting down tREFI --------------------
                S_NORMAL: begin
                    ref_req    <= 1'b0;
                    ref_stall  <= 1'b0;
                    ref_active <= 1'b0;

                    if (trefi_cnt == {TREFI_W{1'b0}}) begin
                        // Interval expired → move to REF_PENDING
                        trefi_cnt <= trefi_val;
                        state     <= S_REF_PENDING;
                        ref_req   <= 1'b1;
                        ref_active<= 1'b1;
                    end else begin
                        // Clamp counter if temp_throttle asserts mid-interval
                        // so the throttled tREFI takes effect immediately.
                        if (trefi_cnt > trefi_val)
                            trefi_cnt <= trefi_val;
                        else
                            trefi_cnt <= trefi_cnt - {{(TREFI_W-1){1'b0}}, 1'b1};
                    end
                end

                // ---- REF_PENDING: wait for banks to drain -----------
                S_REF_PENDING: begin
                    ref_req    <= 1'b1;
                    ref_active <= 1'b1;

                    if (can_refresh) begin
                        // Snapshot REFpb target before issuing
                        if (rfsh_mode) begin
                            ref_bank_group <= bank_idx_group;
                            ref_bank       <= bank_idx_bank;
                        end else begin
                            ref_bank_group <= 2'd0;
                            ref_bank       <= 2'd0;
                        end

                        ref_issue <= 1'b1;
                        ref_stall <= 1'b1;
                        ref_req   <= 1'b0;
                        state     <= S_REFRESHING;
                        trfc_cnt  <= P_TRFC - 1;
                    end
                end

                // ---- REFRESHING: tRFC countdown ---------------------
                S_REFRESHING: begin
                    ref_stall  <= 1'b1;
                    ref_active <= 1'b1;

                    if (trfc_cnt == {TRFC_W{1'b0}}) begin
                        // tRFC done; advance bank index for REFpb
                        if (rfsh_mode) begin
                            if (bank_idx == (TOTAL_BANKS - 1))
                                bank_idx <= {BANK_W{1'b0}};
                            else
                                bank_idx <= bank_idx + {{(BANK_W-1){1'b0}}, 1'b1};
                        end
                        ref_stall  <= 1'b0;
                        ref_active <= 1'b0;
                        state      <= S_NORMAL;
                    end else begin
                        trfc_cnt <= trfc_cnt - {{(TRFC_W-1){1'b0}}, 1'b1};
                    end
                end

                default: state <= S_NORMAL;

            endcase
        end
    end

endmodule

`default_nettype wire

tb/refresh_ctrl_tb.v
// refresh_ctrl_tb.v – Testbench for refresh_ctrl
//
// Uses compact timing parameters to keep simulation fast:
//   P_TREFI = 20 cycles   (REFab/REFpb interval)
//   P_TRFC  = 8  cycles   (refresh cycle time)
//   BANK_GROUPS      = 2
//   BANKS_PER_GROUP  = 2  (→ 4 total banks for REFpb cycling)
//
// Tests:
//   T1:  Reset – state = NORMAL, ref_req=0, ref_stall=0, ref_issue=0
//   T2:  REFab – tREFI expires, ref_req asserted, then ref_issue fires
//   T3:  REFab tRFC stall – ref_stall held for exactly P_TRFC cycles
//   T4:  REFab return – ref_stall de-asserted, state back to NORMAL
//   T5:  Second REFab cycle is triggered automatically (timer re-loaded)
//   T6:  temp_throttle halves tREFI interval
//   T7:  REFpb mode – ref_bank_group / ref_bank cycle through all banks
//   T8:  REFpb – four banks refreshed in order; bank_idx wraps to 0
//   T9:  ref_req de-asserted when all_banks_idle de-asserted (wait extend)
//
// Compile & run:
//   iverilog -g2012 -o build/refresh_ctrl.out tb/refresh_ctrl_tb.v rtl/refresh_ctrl.v
//   vvp build/refresh_ctrl.out

`timescale 1ns/1ps

module refresh_ctrl_tb;

    // ----------------------------------------------------------------
    // Compact parameters for fast simulation
    // ----------------------------------------------------------------
    localparam P_TREFI         = 20;
    localparam P_TRFC          = 8;
    localparam BANK_GROUPS     = 2;
    localparam BANKS_PER_GROUP = 2;
    localparam TOTAL_BANKS     = BANK_GROUPS * BANKS_PER_GROUP;  // 4

    // ----------------------------------------------------------------
    // DUT ports
    // ----------------------------------------------------------------
    reg  clk;
    reg  rst_n;
    reg  all_banks_idle;
    reg  rfsh_mode;
    reg  temp_throttle;

    wire ref_req;
    wire ref_issue;
    wire ref_stall;
    wire ref_active;
    wire [1:0] ref_bank_group;
    wire [1:0] ref_bank;

    // ----------------------------------------------------------------
    // DUT instantiation
    // ----------------------------------------------------------------
    refresh_ctrl #(
        .BANK_GROUPS     (BANK_GROUPS),
        .BANKS_PER_GROUP (BANKS_PER_GROUP),
        .P_TREFI         (P_TREFI),
        .P_TRFC          (P_TRFC)
    ) dut (
        .clk            (clk),
        .rst_n          (rst_n),
        .all_banks_idle (all_banks_idle),
        .rfsh_mode      (rfsh_mode),
        .temp_throttle  (temp_throttle),
        .ref_req        (ref_req),
        .ref_issue      (ref_issue),
        .ref_stall      (ref_stall),
        .ref_active     (ref_active),
        .ref_bank_group (ref_bank_group),
        .ref_bank       (ref_bank)
    );

    // ----------------------------------------------------------------
    // Clock generation – 10 ns period (100 MHz)
    // ----------------------------------------------------------------
    initial clk = 0;
    always #5 clk = ~clk;

    // ----------------------------------------------------------------
    // VCD waveform dump
    // ----------------------------------------------------------------
    initial begin
        $dumpfile("results/phase-ddr4-refresh/refresh_ctrl.vcd");
        $dumpvars(0, refresh_ctrl_tb);
    end

    // ----------------------------------------------------------------
    // Test counters / helpers
    // ----------------------------------------------------------------
    integer pass_count, fail_count;

    task chk;
        input        cond;
        input [31:0] test_id;
        input [255:0] msg;
        begin
            if (cond) begin
                $display("PASS T%0d: %s", test_id, msg);
                pass_count = pass_count + 1;
            end else begin
                $display("FAIL T%0d: %s  (req=%b issue=%b stall=%b active=%b bg=%0d b=%0d)",
                         test_id, msg,
                         ref_req, ref_issue, ref_stall, ref_active,
                         ref_bank_group, ref_bank);
                fail_count = fail_count + 1;
            end
        end
    endtask

    // Advance one clock, sample after rising edge
    task tick;
        begin
            @(posedge clk); #1;
        end
    endtask

    // ----------------------------------------------------------------
    // Main test body
    // ----------------------------------------------------------------
    integer i;
    integer req_seen, issue_seen, stall_cycles;
    integer bank_seen [0:3];
    integer bg_captured, bk_captured;

    initial begin
        pass_count      = 0;
        fail_count      = 0;
        rst_n           = 1'b0;
        all_banks_idle  = 1'b1;
        rfsh_mode       = 1'b0;   // REFab by default
        temp_throttle   = 1'b0;

        // ===========================================================
        // T1: Reset
        // ===========================================================
        repeat(4) @(posedge clk);
        #1;
        chk(ref_req   == 1'b0, 1, "reset: ref_req=0");
        chk(ref_issue == 1'b0, 1, "reset: ref_issue=0");
        chk(ref_stall == 1'b0, 1, "reset: ref_stall=0");
        chk(ref_active== 1'b0, 1, "reset: ref_active=0");

        rst_n = 1'b1;
        @(posedge clk); #1;

        // ===========================================================
        // T2: REFab – ref_req asserted when tREFI expires
        //     Wait up to P_TREFI+5 cycles looking for ref_req
        // ===========================================================
        req_seen = 0;
        for (i = 0; i < P_TREFI + 5; i = i + 1) begin
            tick;
            if (ref_req) begin
                req_seen = 1;
                i = P_TREFI + 5; // exit loop
            end
        end
        chk(req_seen == 1, 2, "REFab: ref_req asserted after tREFI");

        // ===========================================================
        // T3: ref_issue fires exactly one cycle after all_banks_idle
        //     (banks already idle in this TB)
        // ===========================================================
        issue_seen = 0;
        for (i = 0; i < 4; i = i + 1) begin
            tick;
            if (ref_issue) begin
                issue_seen = 1;
                i = 4; // exit loop
            end
        end
        chk(issue_seen == 1, 3, "REFab: ref_issue fires when banks idle");

        // ===========================================================
        // T4: ref_stall held for exactly P_TRFC cycles
        // ===========================================================
        // ref_issue may have just fired; sample stall in this cycle
        if (!ref_stall) tick;  // advance if stall not yet seen
        chk(ref_stall == 1'b1, 4, "REFab: ref_stall asserted at start of tRFC");

        stall_cycles = 0;
        while (ref_stall) begin
            stall_cycles = stall_cycles + 1;
            tick;
        end
        // stall_cycles counts cycles where ref_stall was 1
        chk(stall_cycles == P_TRFC, 4, "REFab: ref_stall lasts P_TRFC cycles");

        // ===========================================================
        // T5: After tRFC ref_stall=0 and ref_active=0 (back to NORMAL)
        // ===========================================================
        chk(ref_stall  == 1'b0, 5, "REFab: ref_stall=0 after tRFC");
        chk(ref_active == 1'b0, 5, "REFab: ref_active=0 after tRFC");
        chk(ref_req    == 1'b0, 5, "REFab: ref_req=0 after tRFC");

        // ===========================================================
        // T6: A second automatic REFab cycle starts after another tREFI
        // ===========================================================
        req_seen = 0;
        for (i = 0; i < P_TREFI + 5; i = i + 1) begin
            tick;
            if (ref_req) begin
                req_seen = 1;
                i = P_TREFI + 5;
            end
        end
        chk(req_seen == 1, 6, "REFab 2nd cycle: ref_req asserted again");

        // drain the second cycle quickly
        for (i = 0; i < P_TRFC + 5; i = i + 1) tick;

        // ===========================================================
        // T7: temp_throttle halves tREFI interval
        //     Enable throttle, measure how many cycles until ref_req
        // ===========================================================
        // First, make sure we are back in NORMAL
        while (ref_active) tick;

        temp_throttle = 1'b1;
        req_seen = 0;
        for (i = 0; i < (P_TREFI/2) + 5; i = i + 1) begin
            tick;
            if (ref_req) begin
                req_seen  = 1;
                i = (P_TREFI/2) + 5;
            end
        end
        chk(req_seen == 1, 7, "temp_throttle: ref_req within tREFI/2+5 cycles");

        // drain
        for (i = 0; i < P_TRFC + 5; i = i + 1) tick;
        temp_throttle = 1'b0;
        while (ref_active) tick;

        // ===========================================================
        // T8: REFpb mode – all 4 banks cycled in order
        // ===========================================================
        rfsh_mode = 1'b1;  // switch to per-bank refresh

        // Collect the ref_bank_group and ref_bank at each ref_issue pulse
        // for 4 cycles (= TOTAL_BANKS = 4)
        begin : refpb_loop
            integer b;
            integer bg_arr [0:3];
            integer bk_arr [0:3];
            integer nref;
            nref = 0;

            for (b = 0; b < TOTAL_BANKS * (P_TREFI + P_TRFC) + 20; b = b + 1) begin
                tick;
                if (ref_issue && nref < TOTAL_BANKS) begin
                    bg_arr[nref] = ref_bank_group;
                    bk_arr[nref] = ref_bank;
                    nref = nref + 1;
                end
            end

            chk(nref == TOTAL_BANKS, 8, "REFpb: all banks refreshed once");

            // Bank indices should cycle 0..TOTAL_BANKS-1 in order:
            //   bank_idx = {bg[1:0], b[1:0]}
            //   bg=bank_idx[3:2], bk=bank_idx[1:0]
            begin : refpb_order_chk
                integer k;
                integer ok;
                ok = 1;
                for (k = 0; k < nref; k = k + 1) begin
                    integer exp_bg, exp_bk;
                    exp_bg = k >> 1;       // k / BANKS_PER_GROUP (=2)
                    exp_bk = k  & 1;       // k % BANKS_PER_GROUP (=2)
                    if (bg_arr[k] !== exp_bg || bk_arr[k] !== exp_bk) ok = 0;
                end
                chk(ok == 1, 8, "REFpb: bank order {bg,bk} = 0..TOTAL_BANKS-1");
            end
        end

        // ===========================================================
        // T9: all_banks_idle=0 extends REF_PENDING
        //     Lower all_banks_idle once ref_req asserts; check that
        //     ref_issue is NOT fired while banks are not idle.
        // ===========================================================
        rfsh_mode      = 1'b0;      // back to REFab
        all_banks_idle = 1'b0;      // banks busy

        while (ref_active) tick;    // wait for NORMAL (after previous cycle)

        // Wait for ref_req to fire
        req_seen   = 0;
        issue_seen = 0;
        for (i = 0; i < P_TREFI + 5; i = i + 1) begin
            tick;
            if (ref_req) req_seen = 1;
            if (ref_issue) issue_seen = 1;
        end
        chk(req_seen   == 1, 9, "T9: ref_req asserted with banks busy");
        chk(issue_seen == 0, 9, "T9: ref_issue NOT fired while banks busy");

        // Now idle the banks → refresh should proceed
        all_banks_idle = 1'b1;
        issue_seen = 0;
        for (i = 0; i < 5; i = i + 1) begin
            tick;
            if (ref_issue) issue_seen = 1;
        end
        chk(issue_seen == 1, 9, "T9: ref_issue fires once banks go idle");

        // drain
        for (i = 0; i < P_TRFC + 5; i = i + 1) tick;

        // ===========================================================
        // Summary
        // ===========================================================
        $display("");
        $display("=== Simulation complete: %0d passed, %0d failed ===",
                 pass_count, fail_count);
        if (fail_count != 0)
            $fatal(1, "One or more checks FAILED");
        $finish;
    end

    // ----------------------------------------------------------------
    // Watchdog: abort after 100 000 cycles
    // ----------------------------------------------------------------
    initial begin
        #1000000;
        $fatal(1, "WATCHDOG: simulation exceeded time limit");
    end

endmodule

results/phase-ddr4-refresh/refresh_ctrl.vcd
$date
	Thu Mar 12 11:09:36 2026
$end
$version
	Icarus Verilog
$end
$timescale
	1ps
$end
$scope module refresh_ctrl_tb $end
$var wire 1 ! ref_stall $end
$var wire 1 " ref_req $end
$var wire 1 # ref_issue $end
$var wire 2 $ ref_bank_group [1:0] $end
$var wire 2 % ref_bank [1:0] $end
$var wire 1 & ref_active $end
$var parameter 32 ' BANKS_PER_GROUP $end
$var parameter 32 ( BANK_GROUPS $end
$var parameter 32 ) P_TREFI $end
$var parameter 32 * P_TRFC $end
$var parameter 64 + TOTAL_BANKS $end
$var reg 1 , all_banks_idle $end
$var reg 1 - clk $end
$var reg 1 . rfsh_mode $end
$var reg 1 / rst_n $end
$var reg 1 0 temp_throttle $end
$var integer 32 1 fail_count [31:0] $end
$var integer 32 2 i [31:0] $end
$var integer 32 3 issue_seen [31:0] $end
$var integer 32 4 pass_count [31:0] $end
$var integer 32 5 req_seen [31:0] $end
$var integer 32 6 stall_cycles [31:0] $end
$scope module dut $end
$var wire 1 , all_banks_idle $end
$var wire 1 7 can_refresh $end
$var wire 1 - clk $end
$var wire 1 . rfsh_mode $end
$var wire 1 / rst_n $end
$var wire 1 0 temp_throttle $end
$var wire 14 8 trefi_val [13:0] $end
$var wire 2 9 bank_idx_group [1:0] $end
$var wire 2 : bank_idx_bank [1:0] $end
$var parameter 32 ; BANKS_PER_GROUP $end
$var parameter 32 < BANK_GROUPS $end
$var parameter 32 = BANK_W $end
$var parameter 32 > P_TREFI $end
$var parameter 32 ? P_TRFC $end
$var parameter 2 @ S_NORMAL $end
$var parameter 2 A S_REFRESHING $end
$var parameter 2 B S_REF_PENDING $end
$var parameter 64 C TOTAL_BANKS $end
$var parameter 32 D TREFI_W $end
$var parameter 32 E TRFC_W $end
$var reg 4 F bank_idx [3:0] $end
$var reg 1 & ref_active $end
$var reg 2 G ref_bank [1:0] $end
$var reg 2 H ref_bank_group [1:0] $end
$var reg 1 # ref_issue $end
$var reg 1 " ref_req $end
$var reg 1 ! ref_stall $end
$var reg 2 I state [1:0] $end
$var reg 14 J trefi_cnt [13:0] $end
$var reg 10 K trfc_cnt [9:0] $end
$upscope $end
$scope begin refpb_loop $end
$var integer 32 L b [31:0] $end
$var integer 32 M nref [31:0] $end
$scope begin refpb_order_chk $end
$var integer 32 N k [31:0] $end
$var integer 32 O ok [31:0] $end
$scope begin $unm_blk_18 $end
$var integer 32 P exp_bg [31:0] $end
$var integer 32 Q exp_bk [31:0] $end
$upscope $end
$upscope $end
$upscope $end
$scope task chk $end
$var reg 1 R cond $end
$var reg 256 S msg [255:0] $end
$var reg 32 T test_id [31:0] $end
$upscope $end
$scope task tick $end
$upscope $end
$upscope $end
$enddefinitions $end
$comment Show the parameter values. $end
$dumpall
b1010 E
b1110 D
b100 C
b1 B
b10 A
b0 @
b1000 ?
b10100 >
b100 =
b10 <
b10 ;
b100 +
b1000 *
b10100 )
b10 (
b10 '
$end
#0
$dumpvars
bx T
bx S
xR
bx Q
bx P
bx O
bx N
bx M
bx L
bx K
bx J
bx I
bx H
bx G
bx F
bx :
bx 9
b10011 8
17
bx 6
bx 5
b0 4
bx 3
bx 2
b0 1
00
0/
0.
0-
1,
x&
bx %
bx $
x#
x"
x!
$end
#5000
b0 9
b0 :
b0 %
b0 G
b0 $
b0 H
0&
0!
0#
0"
b0 F
b0 K
b10011 J
b0 I
1-
#10000
0-
#15000
1-
#20000
0-
#25000
1-
#30000
0-
#35000
1-
#36000
1/
b100 4
b1110010011001010111001101100101011101000011101000100000011100100110010101100110010111110110000101100011011101000110100101110110011001010011110100110000 S
b1 T
1R
#40000
0-
#45000
b10010 J
1-
#46000
b0 2
b0 5
#50000
0-
#55000
b10001 J
1-
#56000
b1 2
#60000
0-
#65000
b10000 J
1-
#66000
b10 2
#70000
0-
#75000
b1111 J
1-
#76000
b11 2
#80000
0-
#85000
b1110 J
1-
#86000
b100 2
#90000
0-
#95000
b1101 J
1-
#96000
b101 2
#100000
0-
#105000
b1100 J
1-
#106000
b110 2
#110000
0-
#115000
b1011 J
1-
#116000
b111 2
#120000
0-
#125000
b1010 J
1-
#126000
b1000 2
#130000
0-
#135000
b1001 J
1-
#136000
b1001 2
#140000
0-
#145000
b1000 J
1-
#146000
b1010 2
#150000
0-
#155000
b111 J
1-
#156000
b1011 2
#160000
0-
#165000
b110 J
1-
#166000
b1100 2
#170000
0-
#175000
b101 J
1-
#176000
b1101 2
#180000
0-
#185000
b100 J
1-
#186000
b1110 2
#190000
0-
#195000
b11 J
1-
#196000
b1111 2
#200000
0-
#205000
b10 J
1-
#206000
b10000 2
#210000
0-
#215000
b1 J
1-
#216000
b10001 2
#220000
0-
#225000
b0 J
1-
#226000
b10010 2
#230000
0-
#235000
1&
1"
b1 I
b10011 J
1-
#236000
b0 3
b101 4
b110000101100010001110100010000001110010011001010110011001011111011100100110010101110001001000000110000101110011011100110110010101110010011101000110010101100100001000000110000101100110011101000110010101110010001000000111010001010010010001010100011001001001 S
b10 T
b0 2
b1 5
#240000
0-
#245000
b111 K
b10 I
0"
1!
1#
1-
#246000
b1 6
b111 4
b101111101110011011101000110000101101100011011000010000001100001011100110111001101100101011100100111010001100101011001000010000001100001011101000010000001110011011101000110000101110010011101000010000001101111011001100010000001110100010100100100011001000011 S
b100 T
b101 2
b1 3
#250000
0-
#255000
b110 K
0#
1-
#256000
b10 6
#260000
0-
#265000
b101 K
1-
#266000
b11 6
#270000
0-
#275000
b100 K
1-
#276000
b100 6
#280000
0-
#285000
b11 K
1-
#286000
b101 6
#290000
0-
#295000
b10 K
1-
#296000
b110 6
#300000
0-
#305000
b1 K
1-
#306000
b111 6
#310000
0-
#315000
b0 K
1-
#316000
b1000 6
#320000
0-
#325000
b0 I
0&
0!
1-
#326000
b0 2
b0 5
b101 T
b1011 4
b10100100100010101000110011000010110001000111010001000000111001001100101011001100101111101110010011001010111000100111101001100000010000001100001011001100111010001100101011100100010000001110100010100100100011001000011 S
#330000
0-
#335000
b10010 J
1-
#336000
b1 2
#340000
0-
#345000
b10001 J
1-
#346000
b10 2
#350000
0-
#355000
b10000 J
1-
#356000
b11 2
#360000
0-
#365000
b1111 J
1-
#366000
b100 2
#370000
0-
#375000
b1110 J
1-
#376000
b101 2
#380000
0-
#385000
b1101 J
1-
#386000
b110 2
#390000
0-
#395000
b1100 J
1-
#396000
b111 2
#400000
0-
#405000
b1011 J
1-
#406000
b1000 2
#410000
0-
#415000
b1010 J
1-
#416000
b1001 2
#420000
0-
#425000
b1001 J
1-
#426000
b1010 2
#430000
0-
#435000
b1000 J
1-
#436000
b1011 2
#440000
0-
#445000
b111 J
1-
#446000
b1100 2
#450000
0-
#455000
b110 J
1-
#456000
b1101 2
#460000
0-
#465000
b101 J
1-
#466000
b1110 2
#470000
0-
#475000
b100 J
1-
#476000
b1111 2
#480000
0-
#485000
b11 J
1-
#486000
b10000 2
#490000
0-
#495000
b10 J
1-
#496000
b10001 2
#500000
0-
#505000
b1 J
1-
#506000
b10010 2
#510000
0-
#515000
b0 J
1-
#516000
b10011 2
#520000
0-
#525000
1&
1"
b1 I
b10011 J
1-
#526000
b1100 4
b110111001100100001000000110001101111001011000110110110001100101001110100010000001110010011001010110011001011111011100100110010101110001001000000110000101110011011100110110010101110010011101000110010101100100001000000110000101100111011000010110100101101110 S
b110 T
b0 2
b1 5
#530000
0-
#535000
b111 K
b10 I
0"
1!
1#
1-
#536000
b1 2
#540000
0-
#545000
b110 K
0#
1-
#546000
b10 2
#550000
0-
#555000
b101 K
1-
#556000
b11 2
#560000
0-
#565000
b100 K
1-
#566000
b100 2
#570000
0-
#575000
b11 K
1-
#576000
b101 2
#580000
0-
#585000
b10 K
1-
#586000
b110 2
#590000
0-
#595000
b1 K
1-
#596000
b111 2
#600000
0-
#605000
b0 K
1-
#606000
b1000 2
#610000
0-
#615000
b0 I
0&
0!
1-
#616000
b1001 2
#620000
0-
#625000
b10010 J
1-
#626000
b1010 2
#630000
0-
#635000
b10001 J
1-
#636000
b1011 2
#640000
0-
#645000
b10000 J
1-
#646000
b1100 2
#650000
0-
#655000
b1111 J
1-
#656000
b1001 8
b0 5
10
b0 2
#660000
0-
#665000
b1001 J
1-
#666000
b1 2
#670000
0-
#675000
b1000 J
1-
#676000
b10 2
#680000
0-
#685000
b111 J
1-
#686000
b11 2
#690000
0-
#695000
b110 J
1-
#696000
b100 2
#700000
0-
#705000
b101 J
1-
#706000
b101 2
#710000
0-
#715000
b100 J
1-
#716000
b110 2
#720000
0-
#725000
b11 J
1-
#726000
b111 2
#730000
0-
#735000
b10 J
1-
#736000
b1000 2
#740000
0-
#745000
b1 J
1-
#746000
b1001 2
#750000
0-
#755000
b0 J
1-
#756000
b1010 2
#760000
0-
#765000
1&
1"
b1 I
b1001 J
1-
#766000
b1101 4
b10000001110010011001010110011001011111011100100110010101110001001000000111011101101001011101000110100001101001011011100010000001110100010100100100010101000110010010010010111100110010001010110011010100100000011000110111100101100011011011000110010101110011 S
b111 T
b0 2
b1 5
#770000
0-
#775000
b111 K
b10 I
0"
1!
1#
1-
#776000
b1 2
#780000
0-
#785000
b110 K
0#
1-
#786000
b10 2
#790000
0-
#795000
b101 K
1-
#796000
b11 2
#800000
0-
#805000
b100 K
1-
#806000
b100 2
#810000
0-
#815000
b11 K
1-
#816000
b101 2
#820000
0-
#825000
b10 K
1-
#826000
b110 2
#830000
0-
#835000
b1 K
1-
#836000
b111 2
#840000
0-
#845000
b0 K
1-
#846000
b1000 2
#850000
0-
#855000
b0 I
0&
0!
1-
#856000
b1001 2
#860000
0-
#865000
b1000 J
1-
#866000
b1010 2
#870000
0-
#875000
b111 J
1-
#876000
b1011 2
#880000
0-
#885000
b110 J
1-
#886000
b1100 2
#890000
0-
#895000
b101 J
1-
#896000
b10011 8
b0 L
b0 M
1.
00
b1101 2
#900000
0-
#905000
b100 J
1-
#906000
b1 L
#910000
0-
#915000
b11 J
1-
#916000
b10 L
#920000
0-
#925000
b10 J
1-
#926000
b11 L
#930000
0-
#935000
b1 J
1-
#936000
b100 L
#940000
0-
#945000
b0 J
1-
#946000
b101 L
#950000
0-
#955000
1&
1"
b1 I
b10011 J
1-
#956000
b110 L
#960000
0-
#965000
b111 K
b10 I
0"
1!
1#
1-
#966000
b111 L
b1 M
#970000
0-
#975000
b110 K
0#
1-
#976000
b1000 L
#980000
0-
#985000
b101 K
1-
#986000
b1001 L
#990000
0-
#995000
b100 K
1-
#996000
b1010 L
#1000000
0-
#1005000
b11 K
1-
#1006000
b1011 L
#1010000
0-
#1015000
b10 K
1-
#1016000
b1100 L
#1020000
0-
#1025000
b1 K
1-
#1026000
b1101 L
#1030000
0-
#1035000
b0 K
1-
#1036000
b1110 L
#1040000
0-
#1045000
b1 :
b0 I
0&
0!
b1 F
1-
#1046000
b1111 L
#1050000
0-
#1055000
b10010 J
1-
#1056000
b10000 L
#1060000
0-
#1065000
b10001 J
1-
#1066000
b10001 L
#1070000
0-
#1075000
b10000 J
1-
#1076000
b10010 L
#1080000
0-
#1085000
b1111 J
1-
#1086000
b10011 L
#1090000
0-
#1095000
b1110 J
1-
#1096000
b10100 L
#1100000
0-
#1105000
b1101 J
1-
#1106000
b10101 L
#1110000
0-
#1115000
b1100 J
1-
#1116000
b10110 L
#1120000
0-
#1125000
b1011 J
1-
#1126000
b10111 L
#1130000
0-
#1135000
b1010 J
1-
#1136000
b11000 L
#1140000
0-
#1145000
b1001 J
1-
#1146000
b11001 L
#1150000
0-
#1155000
b1000 J
1-
#1156000
b11010 L
#1160000
0-
#1165000
b111 J
1-
#1166000
b11011 L
#1170000
0-
#1175000
b110 J
1-
#1176000
b11100 L
#1180000
0-
#1185000
b101 J
1-
#1186000
b11101 L
#1190000
0-
#1195000
b100 J
1-
#1196000
b11110 L
#1200000
0-
#1205000
b11 J
1-
#1206000
b11111 L
#1210000
0-
#1215000
b10 J
1-
#1216000
b100000 L
#1220000
0-
#1225000
b1 J
1-
#1226000
b100001 L
#1230000
0-
#1235000
b0 J
1-
#1236000
b100010 L
#1240000
0-
#1245000
1&
1"
b1 I
b10011 J
1-
#1246000
b100011 L
#1250000
0-
#1255000
b111 K
b10 I
0"
1!
1#
b1 %
b1 G
1-
#1256000
b100100 L
b10 M
#1260000
0-
#1265000
b110 K
0#
1-
#1266000
b100101 L
#1270000
0-
#1275000
b101 K
1-
#1276000
b100110 L
#1280000
0-
#1285000
b100 K
1-
#1286000
b100111 L
#1290000
0-
#1295000
b11 K
1-
#1296000
b101000 L
#1300000
0-
#1305000
b10 K
1-
#1306000
b101001 L
#1310000
0-
#1315000
b1 K
1-
#1316000
b101010 L
#1320000
0-
#1325000
b0 K
1-
#1326000
b101011 L
#1330000
0-
#1335000
b1 9
b0 :
b0 I
0&
0!
b10 F
1-
#1336000
b101100 L
#1340000
0-
#1345000
b10010 J
1-
#1346000
b101101 L
#1350000
0-
#1355000
b10001 J
1-
#1356000
b101110 L
#1360000
0-
#1365000
b10000 J
1-
#1366000
b101111 L
#1370000
0-
#1375000
b1111 J
1-
#1376000
b110000 L
#1380000
0-
#1385000
b1110 J
1-
#1386000
b110001 L
