rtl/cmd_arbiter.v
// cmd_arbiter.v – DDR4 Command Arbiter
//
// Arbitrates between read and write request queues from the AXI slave and
// forwards the selected request to cmd_scheduler using a valid/ready handshake.
//
// Refresh preemption (ref_req from refresh_ctrl):
//   When ref_req is asserted the arbiter stops forwarding new commands to the
//   scheduler.  Any in-flight S_BUSY transaction is allowed to complete first.
//
// Priority policy (parameter RD_PRIORITY):
//   1 = reads preferred over writes when both are pending (default)
//   0 = writes preferred over reads when both are pending
//
// Upstream handshake:
//   rd_ready / wr_ready are single-cycle accept pulses on the cycle the request
//   is latched.  Only one of rd_ready or wr_ready is asserted per cycle.
//
// Downstream handshake:
//   arb_valid is held high until arb_ready is observed from cmd_scheduler.
//
// Reset: active-low asynchronous (negedge rst_n in sensitivity list).
//
// Compile & run:
//   iverilog -g2012 -o build/cmd_arbiter.out tb/cmd_arbiter_tb.v rtl/cmd_arbiter.v
//   vvp build/cmd_arbiter.out

`default_nettype none

module cmd_arbiter #(
    parameter AXI_ADDR_W  = 34,
    parameter AXI_ID_W    = 8,
    parameter RD_PRIORITY = 1    // 1 = reads preferred; 0 = writes preferred
)(
    input  wire                  clk,
    input  wire                  rst_n,

    // Refresh preemption (from refresh_ctrl) – highest priority
    input  wire                  ref_req,     // 1 = block new downstream commands

    // Read request channel (from upstream / axi4_slave)
    input  wire                  rd_valid,
    output reg                   rd_ready,
    input  wire [AXI_ADDR_W-1:0] rd_addr,
    input  wire [AXI_ID_W-1:0]   rd_id,

    // Write request channel (from upstream / axi4_slave)
    input  wire                  wr_valid,
    output reg                   wr_ready,
    input  wire [AXI_ADDR_W-1:0] wr_addr,
    input  wire [AXI_ID_W-1:0]   wr_id,

    // Arbitrated output to cmd_scheduler (valid/ready handshake)
    output reg                   arb_valid,
    input  wire                  arb_ready,
    output reg                   arb_is_write,
    output reg  [AXI_ADDR_W-1:0] arb_addr,
    output reg  [AXI_ID_W-1:0]   arb_id
);

    // ---------------------------------------------------------------
    // FSM state encodings
    // ---------------------------------------------------------------
    localparam S_IDLE = 1'b0;   // no active downstream transaction
    localparam S_BUSY = 1'b1;   // holding arb_valid until arb_ready seen

    reg state;

    // ---------------------------------------------------------------
    // Grant selection – combinational, active only in IDLE
    //
    // prefer_rd is a parameter-derived constant; the synthesizer will
    // eliminate the dead branch entirely.
    // ---------------------------------------------------------------
    wire prefer_rd = (RD_PRIORITY == 1) ? 1'b1 : 1'b0;

    wire can_arb  = (state == S_IDLE) && !ref_req;
    wire grant_rd = can_arb &&  rd_valid && (!wr_valid ||  prefer_rd);
    wire grant_wr = can_arb &&  wr_valid && (!rd_valid || !prefer_rd);

    // ---------------------------------------------------------------
    // Sequential FSM (active-low async reset)
    // ---------------------------------------------------------------
    always @(posedge clk or negedge rst_n) begin
        if (!rst_n) begin
            state        <= S_IDLE;
            arb_valid    <= 1'b0;
            arb_is_write <= 1'b0;
            arb_addr     <= {AXI_ADDR_W{1'b0}};
            arb_id       <= {AXI_ID_W{1'b0}};
            rd_ready     <= 1'b0;
            wr_ready     <= 1'b0;
        end else begin
            // Default: clear single-cycle accept pulses
            rd_ready <= 1'b0;
            wr_ready <= 1'b0;

            case (state)

                // ---------------------------------------------------
                // IDLE: no active downstream transaction.
                // Accept rd or wr if available and refresh permits.
                // ---------------------------------------------------
                S_IDLE: begin
                    arb_valid <= 1'b0;
                    if (grant_rd) begin
                        arb_valid    <= 1'b1;
                        arb_is_write <= 1'b0;
                        arb_addr     <= rd_addr;
                        arb_id       <= rd_id;
                        rd_ready     <= 1'b1;
                        state        <= S_BUSY;
                    end else if (grant_wr) begin
                        arb_valid    <= 1'b1;
                        arb_is_write <= 1'b1;
                        arb_addr     <= wr_addr;
                        arb_id       <= wr_id;
                        wr_ready     <= 1'b1;
                        state        <= S_BUSY;
                    end
                end

                // ---------------------------------------------------
                // BUSY: forwarding request downstream.
                // Hold arb_valid until arb_ready is observed.
                // ---------------------------------------------------
                S_BUSY: begin
                    if (arb_ready) begin
                        arb_valid <= 1'b0;
                        state     <= S_IDLE;
                    end
                end

                default: state <= S_IDLE;

            endcase
        end
    end

endmodule

`default_nettype wire

tb/cmd_arbiter_tb.v
// cmd_arbiter_tb.v – Testbench for cmd_arbiter
//
// Uses compact parameters:
//   AXI_ADDR_W = 10 (narrow address to keep stimulus readable)
//   AXI_ID_W   = 4
//   RD_PRIORITY = 1 (reads preferred over writes)
//
// Tests:
//   T1:  Reset – arb_valid=0, rd_ready=0, wr_ready=0, state=IDLE
//   T2:  Read-only: rd_valid=1, wr_valid=0 → grant read, rd_ready pulse
//   T3:  Write-only: wr_valid=1, rd_valid=0 → grant write, wr_ready pulse
//   T4:  Both valid with RD_PRIORITY=1 → reads win; then wr granted
//   T5:  ref_req asserted → no new grants; backlog granted after deassert
//   T6:  Back-pressure: arb_ready=0 → arb_valid held; accepted when ready=1
//   T7:  Sequential pipeline: back-to-back read requests each granted
//   T8:  ref_req deasserted mid-BUSY: in-flight completes, new grant accepted
//
// Compile & run:
//   iverilog -g2012 -o build/cmd_arbiter.out tb/cmd_arbiter_tb.v rtl/cmd_arbiter.v
//   vvp build/cmd_arbiter.out

`timescale 1ns/1ps

module cmd_arbiter_tb;

    // ----------------------------------------------------------------
    // Parameters
    // ----------------------------------------------------------------
    localparam AXI_ADDR_W  = 10;
    localparam AXI_ID_W    = 4;
    localparam RD_PRIORITY = 1;

    // ----------------------------------------------------------------
    // DUT ports
    // ----------------------------------------------------------------
    reg                   clk;
    reg                   rst_n;
    reg                   ref_req;

    reg                   rd_valid;
    wire                  rd_ready;
    reg  [AXI_ADDR_W-1:0] rd_addr;
    reg  [AXI_ID_W-1:0]   rd_id;

    reg                   wr_valid;
    wire                  wr_ready;
    reg  [AXI_ADDR_W-1:0] wr_addr;
    reg  [AXI_ID_W-1:0]   wr_id;

    wire                  arb_valid;
    reg                   arb_ready;
    wire                  arb_is_write;
    wire [AXI_ADDR_W-1:0] arb_addr;
    wire [AXI_ID_W-1:0]   arb_id;

    // ----------------------------------------------------------------
    // DUT instantiation
    // ----------------------------------------------------------------
    cmd_arbiter #(
        .AXI_ADDR_W  (AXI_ADDR_W),
        .AXI_ID_W    (AXI_ID_W),
        .RD_PRIORITY (RD_PRIORITY)
    ) dut (
        .clk         (clk),
        .rst_n       (rst_n),
        .ref_req     (ref_req),
        .rd_valid    (rd_valid),
        .rd_ready    (rd_ready),
        .rd_addr     (rd_addr),
        .rd_id       (rd_id),
        .wr_valid    (wr_valid),
        .wr_ready    (wr_ready),
        .wr_addr     (wr_addr),
        .wr_id       (wr_id),
        .arb_valid   (arb_valid),
        .arb_ready   (arb_ready),
        .arb_is_write(arb_is_write),
        .arb_addr    (arb_addr),
        .arb_id      (arb_id)
    );

    // ----------------------------------------------------------------
    // Clock generation – 10 ns period (100 MHz)
    // ----------------------------------------------------------------
    initial clk = 0;
    always #5 clk = ~clk;

    // ----------------------------------------------------------------
    // VCD waveform dump
    // ----------------------------------------------------------------
    initial begin
        $dumpfile("results/phase-ddr4-sched/cmd_arbiter.vcd");
        $dumpvars(0, cmd_arbiter_tb);
    end

    // ----------------------------------------------------------------
    // Check helper
    // ----------------------------------------------------------------
    integer pass_count, fail_count;

    task chk;
        input        cond;
        input [31:0] tid;
        input [239:0] msg;
        begin
            if (cond) begin
                $display("PASS T%0d: %s", tid, msg);
                pass_count = pass_count + 1;
            end else begin
                $display("FAIL T%0d: %s  (arb_valid=%b is_wr=%b addr=%h id=%h)",
                         tid, msg, arb_valid, arb_is_write, arb_addr, arb_id);
                fail_count = fail_count + 1;
            end
        end
    endtask

    // Advance one clock cycle
    task clk_cycle;
        begin
            @(posedge clk); #1;
        end
    endtask

    // Accept downstream command on the same cycle arb_valid is seen
    task accept_now;
        begin
            @(negedge clk); arb_ready = 1'b1;
            @(posedge clk); #1;
            arb_ready = 1'b0;
        end
    endtask

    // ----------------------------------------------------------------
    // Main test sequencer
    // ----------------------------------------------------------------
    initial begin
        pass_count = 0;
        fail_count = 0;

        // Default stimulus
        rst_n     = 1'b0;
        ref_req   = 1'b0;
        rd_valid  = 1'b0;
        rd_addr   = {AXI_ADDR_W{1'b0}};
        rd_id     = {AXI_ID_W{1'b0}};
        wr_valid  = 1'b0;
        wr_addr   = {AXI_ADDR_W{1'b0}};
        wr_id     = {AXI_ID_W{1'b0}};
        arb_ready = 1'b0;

        // =============================================================
        // T1: Reset state
        // =============================================================
        repeat(4) @(posedge clk);
        #1;
        chk(arb_valid   == 1'b0, 1, "reset: arb_valid=0");
        chk(rd_ready    == 1'b0, 1, "reset: rd_ready=0");
        chk(wr_ready    == 1'b0, 1, "reset: wr_ready=0");
        chk(arb_is_write == 1'b0, 1, "reset: arb_is_write=0");

        @(posedge clk); #1;
        rst_n = 1'b1;
        @(posedge clk); #1;

        // =============================================================
        // T2: Read-only request
        // =============================================================
        @(negedge clk);
        rd_valid = 1'b1;
        rd_addr  = 10'h0A5;
        rd_id    = 4'h3;

        // arb_ready=0: grant should appear but stall until ready
        @(posedge clk); #1;
        chk(arb_valid    == 1'b1, 2, "rd-only: arb_valid=1 after 1 cycle");
        chk(arb_is_write == 1'b0, 2, "rd-only: arb_is_write=0");
        chk(arb_addr     == 10'h0A5, 2, "rd-only: arb_addr correct");
        chk(arb_id       == 4'h3,    2, "rd-only: arb_id correct");
        chk(rd_ready     == 1'b1, 2, "rd-only: rd_ready pulsed");

        rd_valid = 1'b0;
        // Accept it now
        @(negedge clk); arb_ready = 1'b1;
        @(posedge clk); #1;
        arb_ready = 1'b0;
        chk(arb_valid == 1'b0, 2, "rd-only: arb_valid cleared after accept");

        clk_cycle;

        // =============================================================
        // T3: Write-only request
        // =============================================================
        @(negedge clk);
        wr_valid = 1'b1;
        wr_addr  = 10'h1BC;
        wr_id    = 4'h7;

        @(posedge clk); #1;
        chk(arb_valid    == 1'b1, 3, "wr-only: arb_valid=1");
        chk(arb_is_write == 1'b1, 3, "wr-only: arb_is_write=1");
        chk(arb_addr     == 10'h1BC, 3, "wr-only: arb_addr correct");
        chk(wr_ready     == 1'b1, 3, "wr-only: wr_ready pulsed");
        chk(rd_ready     == 1'b0, 3, "wr-only: rd_ready not asserted");

        wr_valid = 1'b0;
        @(negedge clk); arb_ready = 1'b1;
        @(posedge clk); #1;
        arb_ready = 1'b0;

        clk_cycle;

        // =============================================================
        // T4: Both valid with RD_PRIORITY=1 – reads win
        // =============================================================
        @(negedge clk);
        rd_valid = 1'b1;
        rd_addr  = 10'h0F0;
        rd_id    = 4'h1;
        wr_valid = 1'b1;
        wr_addr  = 10'h0FF;
        wr_id    = 4'h2;

        @(posedge clk); #1;
        chk(arb_is_write == 1'b0,   4, "both-valid RD_PRI=1: read granted");
        chk(arb_addr     == 10'h0F0,4, "both-valid: rd_addr forwarded");
        chk(rd_ready     == 1'b1,   4, "both-valid: rd_ready pulsed");
        chk(wr_ready     == 1'b0,   4, "both-valid: wr_ready NOT pulsed");

        // Accept read; now write should be granted on next idle cycle
        rd_valid = 1'b0;
        @(negedge clk); arb_ready = 1'b1;
        @(posedge clk); #1;
        arb_ready = 1'b0;

        // Wait one more cycle for the write to be scheduled
        @(posedge clk); #1;
        chk(arb_valid    == 1'b1, 4, "both-valid: write granted next");
        chk(arb_is_write == 1'b1, 4, "both-valid: is_write=1 for write");
        chk(arb_addr     == 10'h0FF, 4, "both-valid: wr_addr forwarded");

        wr_valid = 1'b0;
        @(negedge clk); arb_ready = 1'b1;
        @(posedge clk); #1;
        arb_ready = 1'b0;

        clk_cycle;

        // =============================================================
        // T5: ref_req blocks arbitration
        // =============================================================
        @(negedge clk);
        ref_req  = 1'b1;
        rd_valid = 1'b1;
        rd_addr  = 10'h077;
        rd_id    = 4'h5;

        repeat(3) clk_cycle;
        chk(arb_valid == 1'b0, 5, "ref_req: no grant while ref_req=1");
        chk(rd_ready  == 1'b0, 5, "ref_req: rd_ready stays 0");

        // Release ref_req; request should now be granted
        @(negedge clk); ref_req = 1'b0;
        @(posedge clk); #1;
        chk(arb_valid    == 1'b1, 5, "ref_req released: grant issued");
        chk(arb_is_write == 1'b0, 5, "ref_req released: is read");

        rd_valid = 1'b0;
        @(negedge clk); arb_ready = 1'b1;
        @(posedge clk); #1;
        arb_ready = 1'b0;

        clk_cycle;

        // =============================================================
        // T6: Back-pressure: arb_ready=0 holds arb_valid
        // =============================================================
        @(negedge clk);
        wr_valid = 1'b1;
        wr_addr  = 10'h0CC;
        wr_id    = 4'hA;

        @(posedge clk); #1;
        chk(arb_valid == 1'b1, 6, "backpressure: arb_valid asserted");

        // Hold arb_ready=0 for 3 more cycles – arb_valid must stay high
        repeat(3) begin
            clk_cycle;
            chk(arb_valid == 1'b1, 6, "backpressure: arb_valid held high");
        end

        // Now accept
        wr_valid = 1'b0;
        @(negedge clk); arb_ready = 1'b1;
        @(posedge clk); #1;
        arb_ready = 1'b0;
        chk(arb_valid == 1'b0, 6, "backpressure: arb_valid deasserted after accept");

        clk_cycle;

        // =============================================================
        // T7: Sequential pipeline – two back-to-back read requests
        // =============================================================
        @(negedge clk);
        rd_valid = 1'b1;
        rd_addr  = 10'h011;
        rd_id    = 4'hB;

        @(posedge clk); #1;
        chk(arb_valid == 1'b1, 7, "pipeline req1: arb_valid=1");
        chk(arb_addr  == 10'h011, 7, "pipeline req1: addr correct");

        // Accept req1; present req2 simultaneously
        rd_addr = 10'h022;
        rd_id   = 4'hC;
        @(negedge clk); arb_ready = 1'b1;
        @(posedge clk); #1;
        arb_ready = 1'b0;

        // After accepting req1, req2 should be picked up next cycle
        @(posedge clk); #1;
        chk(arb_valid == 1'b1, 7, "pipeline req2: arb_valid=1");
        chk(arb_addr  == 10'h022, 7, "pipeline req2: addr correct");

        rd_valid = 1'b0;
        @(negedge clk); arb_ready = 1'b1;
        @(posedge clk); #1;
        arb_ready = 1'b0;

        clk_cycle;

        // =============================================================
        // T8: ref_req during BUSY does not abort in-flight transaction
        // =============================================================
        @(negedge clk);
        rd_valid = 1'b1;
        rd_addr  = 10'h033;

        @(posedge clk); #1;
        chk(arb_valid == 1'b1, 8, "in-flight: arb_valid asserted");

        // Assert ref_req while arb is BUSY
        @(negedge clk); ref_req = 1'b1; arb_ready = 1'b0; rd_valid = 1'b0;
        clk_cycle;
        chk(arb_valid == 1'b1, 8, "in-flight+ref_req: arb_valid still high");

        // Complete the in-flight transaction despite ref_req
        @(negedge clk); arb_ready = 1'b1;
        @(posedge clk); #1;
        arb_ready = 1'b0;
        chk(arb_valid == 1'b0, 8, "in-flight: cleared after accept");

        ref_req = 1'b0;
        clk_cycle;

        // =============================================================
        // Summary
        // =============================================================
        $display("--------------------------------------------");
        $display("cmd_arbiter_tb: %0d PASSED, %0d FAILED",
                 pass_count, fail_count);
        $display("--------------------------------------------");
        if (fail_count != 0) $fatal(1, "cmd_arbiter_tb: simulation FAILED");
        $finish;
    end

endmodule

results/phase-ddr4-sched/cmd_arbiter.vcd
$date
	Thu Mar 12 11:32:41 2026
$end
$version
	Icarus Verilog
$end
$timescale
	1ps
$end
$scope module cmd_arbiter_tb $end
$var wire 1 ! wr_ready $end
$var wire 1 " rd_ready $end
$var wire 1 # arb_valid $end
$var wire 1 $ arb_is_write $end
$var wire 4 % arb_id [3:0] $end
$var wire 10 & arb_addr [9:0] $end
$var parameter 32 ' AXI_ADDR_W $end
$var parameter 32 ( AXI_ID_W $end
$var parameter 32 ) RD_PRIORITY $end
$var reg 1 * arb_ready $end
$var reg 1 + clk $end
$var reg 10 , rd_addr [9:0] $end
$var reg 4 - rd_id [3:0] $end
$var reg 1 . rd_valid $end
$var reg 1 / ref_req $end
$var reg 1 0 rst_n $end
$var reg 10 1 wr_addr [9:0] $end
$var reg 4 2 wr_id [3:0] $end
$var reg 1 3 wr_valid $end
$var integer 32 4 fail_count [31:0] $end
$var integer 32 5 pass_count [31:0] $end
$scope module dut $end
$var wire 1 * arb_ready $end
$var wire 1 6 can_arb $end
$var wire 1 + clk $end
$var wire 1 7 grant_rd $end
$var wire 1 8 grant_wr $end
$var wire 1 9 prefer_rd $end
$var wire 10 : rd_addr [9:0] $end
$var wire 4 ; rd_id [3:0] $end
$var wire 1 . rd_valid $end
$var wire 1 / ref_req $end
$var wire 1 0 rst_n $end
$var wire 10 < wr_addr [9:0] $end
$var wire 4 = wr_id [3:0] $end
$var wire 1 3 wr_valid $end
$var parameter 32 > AXI_ADDR_W $end
$var parameter 32 ? AXI_ID_W $end
$var parameter 32 @ RD_PRIORITY $end
$var parameter 1 A S_BUSY $end
$var parameter 1 B S_IDLE $end
$var reg 10 C arb_addr [9:0] $end
$var reg 4 D arb_id [3:0] $end
$var reg 1 $ arb_is_write $end
$var reg 1 # arb_valid $end
$var reg 1 " rd_ready $end
$var reg 1 E state $end
$var reg 1 ! wr_ready $end
$upscope $end
$scope task accept_now $end
$upscope $end
$scope task chk $end
$var reg 1 F cond $end
$var reg 240 G msg [239:0] $end
$var reg 32 H tid [31:0] $end
$upscope $end
$scope task clk_cycle $end
$upscope $end
$upscope $end
$enddefinitions $end
$comment Show the parameter values. $end
$dumpall
0B
1A
b1 @
b100 ?
b1010 >
b1 )
b100 (
b1010 '
$end
#0
$dumpvars
bx H
bx G
xF
0E
b0 D
b0 C
b0 =
b0 <
b0 ;
b0 :
19
08
07
16
b0 5
b0 4
03
b0 2
b0 1
00
0/
0.
b0 -
b0 ,
0+
0*
b0 &
b0 %
0$
0#
0"
0!
$end
#5000
1+
#10000
0+
#15000
1+
#20000
0+
#25000
1+
#30000
0+
#35000
1+
#36000
b100 5
b11100100110010101110011011001010111010000111010001000000110000101110010011000100101111101101001011100110101111101110111011100100110100101110100011001010011110100110000 G
b1 H
1F
#40000
0+
#45000
1+
#46000
10
#50000
0+
#55000
1+
#60000
17
b11 -
b11 ;
b10100101 ,
b10100101 :
1.
0+
#65000
07
06
1E
1"
b11 %
b11 D
b10100101 &
b10100101 C
1#
1+
#66000
0.
b1001 5
b11100100110010000101101011011110110111001101100011110010011101000100000011100100110010001011111011100100110010101100001011001000111100100100000011100000111010101101100011100110110010101100100 G
b10 H
#70000
1*
0+
#75000
16
0E
0#
0"
1+
#76000
b1010 5
b11000010111001001100010010111110111011001100001011011000110100101100100001000000110001101101100011001010110000101110010011001010110010000100000011000010110011001110100011001010111001000100000011000010110001101100011011001010111000001110100 G
0*
#80000
0+
#85000
1+
#90000
18
b111 2
b111 =
b110111100 1
b110111100 <
13
0+
#95000
08
06
1E
1!
b111 %
b111 D
b110111100 &
b110111100 C
1$
1#
1+
#96000
03
b1111 5
b11101110111001000101101011011110110111001101100011110010011101000100000011100100110010001011111011100100110010101100001011001000111100100100000011011100110111101110100001000000110000101110011011100110110010101110010011101000110010101100100 G
b11 H
#100000
1*
0+
#105000
16
0E
0#
0!
1+
#106000
0*
#110000
0+
#115000
1+
#120000
17
b10 2
b10 =
b11111111 1
b11111111 <
13
b1 -
b1 ;
b11110000 ,
b11110000 :
1.
0+
#125000
07
06
1E
1"
b1 %
b1 D
b11110000 &
b11110000 C
0$
1#
1+
#126000
0.
b10011 5
b11011110111010001101000001011010111011001100001011011000110100101100100001110100010000001110111011100100101111101110010011001010110000101100100011110010010000001001110010011110101010000100000011100000111010101101100011100110110010101100100 G
b100 H
#130000
1*
0+
#135000
18
16
0E
0#
0"
1+
#136000
0*
#140000
0+
#145000
08
06
1E
1!
b10 %
b10 D
b11111111 &
b11111111 C
1$
1#
1+
#146000
03
b10110 5
b110001001101111011101000110100000101101011101100110000101101100011010010110010000111010001000000111011101110010010111110110000101100100011001000111001000100000011001100110111101110010011101110110000101110010011001000110010101100100 G
#150000
1*
0+
#155000
16
0E
0#
0!
1+
#156000
0*
#160000
0+
#165000
1+
#170000
06
b101 -
b101 ;
b1110111 ,
b1110111 :
1.
1/
0+
#175000
1+
#180000
0+
#185000
1+
#190000
0+
#195000
1+
#196000
b11000 5
b1110010011001010110011001011111011100100110010101110001001110100010000001110010011001000101111101110010011001010110000101100100011110010010000001110011011101000110000101111001011100110010000000110000 G
b101 H
#200000
17
16
0/
0+
#205000
07
06
1E
1"
b101 %
b101 D
b1110111 &
b1110111 C
0$
1#
1+
#206000
0.
b11010 5
b1110010011001010110011001011111011100100110010101110001001000000111001001100101011011000110010101100001011100110110010101100100001110100010000001101001011100110010000001110010011001010110000101100100 G
#210000
1*
0+
#215000
16
0E
0#
0"
1+
#216000
0*
#220000
0+
#225000
1+
#230000
18
b1010 2
b1010 =
b11001100 1
b11001100 <
13
0+
#235000
08
06
1E
1!
b1010 %
b1010 D
b11001100 &
b11001100 C
1$
1#
1+
#236000
b11011 5
b11000110110101101110000011100100110010101110011011100110111010101110010011001010011101000100000011000010111001001100010010111110111011001100001011011000110100101100100001000000110000101110011011100110110010101110010011101000110010101100100 G
b110 H
#240000
0+
#245000
0!
1+
#246000
b11100 5
b11010110111000001110010011001010111001101110011011101010111001001100101001110100010000001100001011100100110001001011111011101100110000101101100011010010110010000100000011010000110010101101100011001000010000001101000011010010110011101101000 G
#250000
0+
#255000
1+
#256000
b11101 5
#260000
0+
#265000
1+
#266000
03
b11110 5
#270000
1*
0+
#275000
16
0E
0#
1+
#276000
b11111 5
b10111110111011001100001011011000110100101100100001000000110010001100101011000010111001101110011011001010111001001110100011001010110010000100000011000010110011001110100011001010111001000100000011000010110001101100011011001010111000001110100 G
0*
#280000
0+
#285000
1+
#290000
17
b1011 -
b1011 ;
b10001 ,
b10001 :
1.
0+
#295000
07
06
1E
1"
b1011 %
b1011 D
b10001 &
b10001 C
0$
1#
1+
#296000
b1100 -
b1100 ;
b100010 ,
b100010 :
b100001 5
b11100000110100101110000011001010110110001101001011011100110010100100000011100100110010101110001001100010011101000100000011000010110010001100100011100100010000001100011011011110111001001110010011001010110001101110100 G
b111 H
#300000
1*
0+
#305000
17
16
0E
0#
0"
1+
#306000
0*
#310000
0+
#315000
07
06
1E
1"
b1100 %
b1100 D
b100010 &
b100010 C
1#
1+
#316000
0.
b100011 5
b11100000110100101110000011001010110110001101001011011100110010100100000011100100110010101110001001100100011101000100000011000010110010001100100011100100010000001100011011011110111001001110010011001010110001101110100 G
#320000
1*
0+
#325000
16
0E
0#
0"
1+
#326000
0*
#330000
0+
#335000
1+
#340000
17
b110011 ,
b110011 :
1.
0+
#345000
07
06
1E
1"
b110011 &
b110011 C
1#
1+
#346000
b100100 5
b110100101101110001011010110011001101100011010010110011101101000011101000011101000100000011000010111001001100010010111110111011001100001011011000110100101100100001000000110000101110011011100110110010101110010011101000110010101100100 G
b1000 H
#350000
0.
1/
0+
#355000
0"
1+
#356000
b100101 5
b1010110111001001100101011001100101111101110010011001010111000100111010001000000110000101110010011000100101111101110110011000010110110001101001011001000010000001110011011101000110100101101100011011000010000001101000011010010110011101101000 G
#360000
1*
0+
#365000
0E
0#
1+
#366000
16
0/
b100110 5
b11011100010110101100110011011000110100101100111011010000111010000111010001000000110001101101100011001010110000101110010011001010110010000100000011000010110011001110100011001010111001000100000011000010110001101100011011001010111000001110100 G
0*
