rtl/bank_fsm.v
// bank_fsm.v – Per-bank state machine for DDR4 controller
//
// Implements the four-state bank FSM described in docs/ARCHITECTURE.md §6.1:
//   IDLE -> ACTIVATING -> ACTIVE -> PRECHARGING -> IDLE
//
// Timing constraints enforced:
//   P_TRCD : cycles from ACT to first RD/WR (dwell time in ACTIVATING)
//   P_TRAS : minimum active time (ACT to earliest PRE); tRAS_timer tracks this
//   P_TRP  : precharge recovery time (dwell time in PRECHARGING)
//
// The tRAS timer starts simultaneously with the ACT command so it counts
// through both ACTIVATING and ACTIVE states.  A PRE command is accepted only
// when tras_ok is asserted (tras_cnt has reached 0).
//
// Interface (from docs/ARCHITECTURE.md §3.2):
//   cmd_in       [2:0]            – command: NOP/ACT/RD/WR/PRE/REF
//   row_addr_in  [ROW_ADDR_W-1:0] – row address carried with ACT
//   cmd_valid                     – command qualified this cycle
//   fsm_ready                     – bank FSM ready to accept a command
//   open_row     [ROW_ADDR_W-1:0] – currently open row (valid in ACTIVE)
//   row_active                    – 1 when in ACTIVE state
//   tras_ok                       – 1 when tRAS constraint satisfied
//   state_out    [1:0]            – raw state for debug
//
// Reset: active-low ASYNCHRONOUS (negedge rst_n in sensitivity list).
//
// Counter initialisation note:
//   trcd_cnt is loaded with (P_TRCD – 2) so that ACTIVATING lasts exactly
//   P_TRCD clock cycles before the FSM enters ACTIVE.
//   trp_cnt  is loaded with (P_TRP  – 2) so that PRECHARGING lasts exactly
//   P_TRP  clock cycles before the FSM returns to IDLE.
//   tras_cnt is loaded with (P_TRAS – 1) so that tras_ok asserts exactly
//   P_TRAS clock cycles after the ACT command.
//   Both P_TRCD and P_TRP must be >= 2 (satisfied by all DDR4 speed grades).
//
// Compile & run:
//   iverilog -g2012 -o build/bank_fsm.out tb/bank_fsm_tb.v rtl/bank_fsm.v
//   vvp build/bank_fsm.out

`default_nettype none

module bank_fsm #(
    parameter ROW_ADDR_W = 17,
    parameter P_TRCD     = 14,  // ACT-to-RD/WR delay (clock cycles, >= 2)
    parameter P_TRAS     = 52,  // Minimum active time (clock cycles)
    parameter P_TRP      = 14   // Precharge recovery time (clock cycles, >= 2)
)(
    input  wire                  clk,
    input  wire                  rst_n,

    // Command interface (driven by cmd_scheduler)
    input  wire [2:0]            cmd_in,
    input  wire [ROW_ADDR_W-1:0] row_addr_in,
    input  wire                  cmd_valid,

    // Status / handshake outputs
    output reg                   fsm_ready,   // bank can accept a command
    output reg  [ROW_ADDR_W-1:0] open_row,    // open row address (valid in ACTIVE)
    output reg                   row_active,  // 1 when in ACTIVE state
    output wire                  tras_ok,     // 1 when tRAS constraint satisfied
    output reg  [1:0]            state_out    // current state (for debug)
);

    // ---------------------------------------------------------------
    // Command encodings (matches cmd_scheduler convention)
    // ---------------------------------------------------------------
    localparam CMD_NOP = 3'd0;
    localparam CMD_ACT = 3'd1;
    localparam CMD_RD  = 3'd2;
    localparam CMD_WR  = 3'd3;
    localparam CMD_PRE = 3'd4;
    localparam CMD_REF = 3'd5;

    // ---------------------------------------------------------------
    // State encodings
    // ---------------------------------------------------------------
    localparam S_IDLE        = 2'd0;
    localparam S_ACTIVATING  = 2'd1;
    localparam S_ACTIVE      = 2'd2;
    localparam S_PRECHARGING = 2'd3;

    // ---------------------------------------------------------------
    // Pre-computed counter load values (localparams keep the math
    // in one place and avoid per-cycle parameter arithmetic)
    // ---------------------------------------------------------------
    localparam [7:0] INIT_TRCD = P_TRCD - 2;  // counts down to 0 in ACTIVATING
    localparam [7:0] INIT_TRAS = P_TRAS - 1;  // counts down to 0 across ACT+ACTIVE
    localparam [7:0] INIT_TRP  = P_TRP  - 2;  // counts down to 0 in PRECHARGING

    // ---------------------------------------------------------------
    // Registers
    // ---------------------------------------------------------------
    reg [1:0] state;
    reg [7:0] trcd_cnt;   // tRCD down-counter
    reg [7:0] tras_cnt;   // tRAS down-counter (runs from ACT)
    reg [7:0] trp_cnt;    // tRP  down-counter

    // tras_ok is combinational: asserted when tras_cnt has reached zero
    assign tras_ok = (tras_cnt == 8'd0);

    // ---------------------------------------------------------------
    // Sequential FSM
    // ---------------------------------------------------------------
    always @(posedge clk or negedge rst_n) begin
        if (!rst_n) begin
            state    <= S_IDLE;
            trcd_cnt <= 8'd0;
            tras_cnt <= 8'd0;
            trp_cnt  <= 8'd0;
            open_row <= {ROW_ADDR_W{1'b0}};
        end else begin
            case (state)

                // ---- IDLE: precharged, waiting for ACTIVATE --------
                S_IDLE: begin
                    if (cmd_valid && cmd_in == CMD_ACT) begin
                        open_row <= row_addr_in;
                        trcd_cnt <= INIT_TRCD;
                        tras_cnt <= INIT_TRAS;
                        state    <= S_ACTIVATING;
                    end
                end

                // ---- ACTIVATING: tRCD and tRAS both counting -------
                S_ACTIVATING: begin
                    // tRAS timer continues to run
                    if (tras_cnt != 8'd0) tras_cnt <= tras_cnt - 8'd1;

                    // tRCD timer controls exit to ACTIVE
                    if (trcd_cnt == 8'd0) begin
                        state <= S_ACTIVE;
                    end else begin
                        trcd_cnt <= trcd_cnt - 8'd1;
                    end
                end

                // ---- ACTIVE: row open; RD/WR accepted --------------
                S_ACTIVE: begin
                    // tRAS timer continues until satisfied
                    if (tras_cnt != 8'd0) tras_cnt <= tras_cnt - 8'd1;

                    // PRE only accepted when tRAS constraint is met
                    if (cmd_valid && cmd_in == CMD_PRE && tras_ok) begin
                        trp_cnt <= INIT_TRP;
                        state   <= S_PRECHARGING;
                    end
                end

                // ---- PRECHARGING: waiting tRP before returning -----
                S_PRECHARGING: begin
                    if (trp_cnt == 8'd0) begin
                        state <= S_IDLE;
                    end else begin
                        trp_cnt <= trp_cnt - 8'd1;
                    end
                end

                default: state <= S_IDLE;

            endcase
        end
    end

    // ---------------------------------------------------------------
    // Combinational output logic
    // ---------------------------------------------------------------
    always @(*) begin
        case (state)
            S_IDLE:        begin fsm_ready = 1'b1; row_active = 1'b0; end
            S_ACTIVATING:  begin fsm_ready = 1'b0; row_active = 1'b0; end
            S_ACTIVE:      begin fsm_ready = 1'b1; row_active = 1'b1; end
            S_PRECHARGING: begin fsm_ready = 1'b0; row_active = 1'b0; end
            default:       begin fsm_ready = 1'b0; row_active = 1'b0; end
        endcase
        state_out = state;
    end

endmodule

`default_nettype wire

tb/bank_fsm_tb.v
// bank_fsm_tb.v – Testbench for bank_fsm (per-bank DDR4 state machine)
//
// Uses compact timing parameters to keep simulation fast:
//   P_TRCD = 4 cycles (ACT to RD/WR)
//   P_TRAS = 8 cycles (minimum active time)
//   P_TRP  = 4 cycles (precharge recovery)
//
// Tests:
//   T1: Reset – state = IDLE, fsm_ready = 1, row_active = 0, open_row = 0
//   T2: ACT in IDLE – transitions to ACTIVATING, row address latched
//   T3: ACTIVATING dwell – exactly P_TRCD cycles before entering ACTIVE
//   T4: tRAS enforcement – PRE issued immediately on entering ACTIVE is blocked
//       (tras_ok is guaranteed 0 here since P_TRAS > P_TRCD)
//   T5: ACTIVE state – RD/WR do not cause a state transition
//   T6: tras_ok asserts after P_TRAS cycles; PRE → PRECHARGING
//   T7: PRECHARGING dwell – exactly P_TRP cycles
//   T8: Return to IDLE after tRP
//   T9: Full second cycle – ACT → ACTIVE → PRE → IDLE
//  T10: open_row preserved across multiple RD/WR commands
//
// Compile & run:
//   iverilog -g2012 -o build/bank_fsm.out tb/bank_fsm_tb.v rtl/bank_fsm.v
//   vvp build/bank_fsm.out

`timescale 1ns/1ps

module bank_fsm_tb;

    // ----------------------------------------------------------------
    // Parameters under test (compact values for simulation speed)
    // ----------------------------------------------------------------
    localparam P_TRCD     = 4;
    localparam P_TRAS     = 8;
    localparam P_TRP      = 4;
    localparam ROW_ADDR_W = 17;

    // ----------------------------------------------------------------
    // DUT ports
    // ----------------------------------------------------------------
    reg                   clk;
    reg                   rst_n;
    reg  [2:0]            cmd_in;
    reg  [ROW_ADDR_W-1:0] row_addr_in;
    reg                   cmd_valid;

    wire                   fsm_ready;
    wire [ROW_ADDR_W-1:0]  open_row;
    wire                   row_active;
    wire                   tras_ok;
    wire [1:0]             state_out;

    // ----------------------------------------------------------------
    // DUT instantiation
    // ----------------------------------------------------------------
    bank_fsm #(
        .ROW_ADDR_W (ROW_ADDR_W),
        .P_TRCD     (P_TRCD),
        .P_TRAS     (P_TRAS),
        .P_TRP      (P_TRP)
    ) dut (
        .clk         (clk),
        .rst_n       (rst_n),
        .cmd_in      (cmd_in),
        .row_addr_in (row_addr_in),
        .cmd_valid   (cmd_valid),
        .fsm_ready   (fsm_ready),
        .open_row    (open_row),
        .row_active  (row_active),
        .tras_ok     (tras_ok),
        .state_out   (state_out)
    );

    // ----------------------------------------------------------------
    // Command / state constants (mirror RTL localparams)
    // ----------------------------------------------------------------
    localparam CMD_NOP = 3'd0;
    localparam CMD_ACT = 3'd1;
    localparam CMD_RD  = 3'd2;
    localparam CMD_WR  = 3'd3;
    localparam CMD_PRE = 3'd4;

    localparam S_IDLE        = 2'd0;
    localparam S_ACTIVATING  = 2'd1;
    localparam S_ACTIVE      = 2'd2;
    localparam S_PRECHARGING = 2'd3;

    // ----------------------------------------------------------------
    // Clock generation – 10 ns period (100 MHz)
    // ----------------------------------------------------------------
    initial clk = 0;
    always #5 clk = ~clk;

    // ----------------------------------------------------------------
    // VCD waveform dump
    // ----------------------------------------------------------------
    initial begin
        $dumpfile("results/phase-ddr4-bank/bank_fsm.vcd");
        $dumpvars(0, bank_fsm_tb);
    end

    // ----------------------------------------------------------------
    // Check helper
    // ----------------------------------------------------------------
    integer pass_count, fail_count;

    task chk;
        input        cond;
        input [31:0] test_id;
        input [159:0] msg;
        begin
            if (cond) begin
                $display("PASS T%0d: %s", test_id, msg);
                pass_count = pass_count + 1;
            end else begin
                $display("FAIL T%0d: %s  (state=%0d rdy=%b act=%b tok=%b)",
                         test_id, msg, state_out, fsm_ready, row_active, tras_ok);
                fail_count = fail_count + 1;
            end
        end
    endtask

    // ----------------------------------------------------------------
    // send_cmd: set cmd on next clock boundary, returns after the
    // *following* rising edge (i.e. the command is captured by DUT).
    // cmd_valid is left HIGH on exit; caller must deassert.
    // ----------------------------------------------------------------
    task send_cmd;
        input [2:0]            c;
        input [ROW_ADDR_W-1:0] raddr;
        begin
            // Set up command between clock edges for clean hold time
            @(negedge clk);
            cmd_in      = c;
            row_addr_in = raddr;
            cmd_valid   = 1'b1;
            // Advance past the next rising edge
            @(posedge clk); #1;
        end
    endtask

    task idle_cycle;
        begin
            @(negedge clk);
            cmd_valid = 1'b0;
            cmd_in    = CMD_NOP;
            @(posedge clk); #1;
        end
    endtask

    // ----------------------------------------------------------------
    // Main test sequencer
    // ----------------------------------------------------------------
    integer i;
    reg [ROW_ADDR_W-1:0] test_row;

    initial begin
        pass_count  = 0;
        fail_count  = 0;

        cmd_in      = CMD_NOP;
        row_addr_in = {ROW_ADDR_W{1'b0}};
        cmd_valid   = 1'b0;

        // ===========================================================
        // T1: Reset
        // ===========================================================
        rst_n = 1'b0;
        repeat(4) @(posedge clk);
        #1;
        chk(state_out  == S_IDLE,                 1, "reset: state=IDLE");
        chk(fsm_ready  == 1'b1,                   1, "reset: fsm_ready=1");
        chk(row_active == 1'b0,                   1, "reset: row_active=0");
        chk(open_row   == {ROW_ADDR_W{1'b0}},     1, "reset: open_row=0");

        @(posedge clk); #1;
        rst_n = 1'b1;
        @(posedge clk); #1;

        // ===========================================================
        // T2: ACT in IDLE -> ACTIVATING; row address latched
        // ===========================================================
        test_row = 17'h1A5B3;
        send_cmd(CMD_ACT, test_row);
        cmd_valid = 1'b0;
        chk(state_out == S_ACTIVATING, 2, "post-ACT: state=ACTIVATING");
        chk(open_row  == test_row,     2, "post-ACT: open_row latched");
        chk(fsm_ready == 1'b0,        2, "post-ACT: fsm_ready=0");

        // ===========================================================
        // T3: ACTIVATING dwell – P_TRCD cycles exactly
        //   T2 consumed 1 cycle; need P_TRCD-2 more in ACTIVATING,
        //   then 1 more to see ACTIVE.
        // ===========================================================
        repeat(P_TRCD - 2) begin
            idle_cycle;
            chk(state_out == S_ACTIVATING, 3, "ACTIVATING dwell");
            chk(fsm_ready == 1'b0,         3, "ACTIVATING: fsm_ready=0");
        end

        // Next cycle: FSM should move to ACTIVE
        idle_cycle;
        chk(state_out == S_ACTIVE, 3, "after tRCD: state=ACTIVE");
        chk(fsm_ready == 1'b1,    3, "ACTIVE: fsm_ready=1");
        chk(row_active == 1'b1,   3, "ACTIVE: row_active=1");

        // ===========================================================
        // T4: tRAS enforcement – premature PRE is blocked
        //   tras_ok MUST be 0 here (P_TRAS > P_TRCD, guaranteed by
        //   JEDEC: tRAS min > tRCD min). Assert this is true first.
        // ===========================================================
        chk(tras_ok == 1'b0, 4, "tRAS not yet satisfied on ACTIVE entry");

        // Issue PRE while tras_ok = 0 – must be silently discarded
        send_cmd(CMD_PRE, {ROW_ADDR_W{1'b0}});
        cmd_valid = 1'b0;
        chk(state_out == S_ACTIVE, 4, "PRE before tRAS: state stays ACTIVE");
        chk(row_active == 1'b1,    4, "PRE before tRAS: row still active");

        // ===========================================================
        // T5: RD and WR in ACTIVE – no state change
        // ===========================================================
        send_cmd(CMD_RD, test_row);
        cmd_valid = 1'b0;
        chk(state_out == S_ACTIVE, 5, "RD: state remains ACTIVE");

        send_cmd(CMD_WR, test_row);
        cmd_valid = 1'b0;
        chk(state_out == S_ACTIVE, 5, "WR: state remains ACTIVE");

        // ===========================================================
        // T6: tras_ok asserts after P_TRAS total cycles; PRE accepted
        // ===========================================================
        i = 0;
        while (!tras_ok && i < 64) begin
            idle_cycle;
            i = i + 1;
        end
        chk(tras_ok == 1'b1, 6, "tRAS satisfied: tras_ok=1");

        // Issue PRE now that tras_ok is high
        send_cmd(CMD_PRE, {ROW_ADDR_W{1'b0}});
        cmd_valid = 1'b0;
        chk(state_out == S_PRECHARGING, 6, "post-PRE: state=PRECHARGING");
        chk(fsm_ready  == 1'b0,         6, "PRECHARGING: fsm_ready=0");
        chk(row_active == 1'b0,         6, "PRECHARGING: row_active=0");

        // ===========================================================
        // T7: PRECHARGING dwell – P_TRP cycles
        //   T6 consumed 1 cycle; check P_TRP-2 more are PRECHARGING,
        //   then 1 more should be IDLE.
        // ===========================================================
        repeat(P_TRP - 2) begin
            idle_cycle;
            chk(state_out == S_PRECHARGING, 7, "PRECHARGING dwell");
            chk(fsm_ready  == 1'b0,          7, "PRECHARGING: fsm_ready=0");
        end

        // ===========================================================
        // T8: After tRP – state = IDLE
        // ===========================================================
        idle_cycle;
        chk(state_out == S_IDLE, 8, "after tRP: state=IDLE");
        chk(fsm_ready == 1'b1,   8, "IDLE: fsm_ready=1");
        chk(row_active == 1'b0,  8, "IDLE: row_active=0");

        // ===========================================================
        // T9: Full second ACT→ACTIVE→PRE→IDLE cycle
        // ===========================================================
        test_row = 17'h0F0F0;
        send_cmd(CMD_ACT, test_row);
        cmd_valid = 1'b0;

        // Wait for ACTIVE
        i = 0;
        while (state_out != S_ACTIVE && i < 32) begin
            idle_cycle;
            i = i + 1;
        end
        chk(state_out == S_ACTIVE, 9, "2nd cycle: reached ACTIVE");
        chk(open_row  == test_row,  9, "2nd cycle: open_row updated");

        // Wait for tras_ok then issue PRE
        i = 0;
        while (!tras_ok && i < 64) begin
            idle_cycle;
            i = i + 1;
        end
        send_cmd(CMD_PRE, {ROW_ADDR_W{1'b0}});
        cmd_valid = 1'b0;
        chk(state_out == S_PRECHARGING, 9, "2nd cycle: PRECHARGING");

        // Wait for IDLE
        i = 0;
        while (state_out != S_IDLE && i < 32) begin
            idle_cycle;
            i = i + 1;
        end
        chk(state_out == S_IDLE, 9, "2nd cycle: back to IDLE");

        // ===========================================================
        // T10: open_row preserved across multiple RD/WR commands
        // ===========================================================
        test_row = 17'h12345;
        send_cmd(CMD_ACT, test_row);
        cmd_valid = 1'b0;

        i = 0;
        while (state_out != S_ACTIVE && i < 32) begin
            idle_cycle;
            i = i + 1;
        end

        repeat(4) begin
            send_cmd(CMD_RD, test_row);
            cmd_valid = 1'b0;
        end
        chk(open_row  == test_row,  10, "open_row stable across RD bursts");
        chk(state_out == S_ACTIVE,  10, "state ACTIVE across RD bursts");

        // ===========================================================
        // Summary
        // ===========================================================
        $display("--------------------------------------------");
        $display("bank_fsm_tb: %0d PASSED, %0d FAILED", pass_count, fail_count);
        $display("--------------------------------------------");
        if (fail_count != 0) $fatal(1, "bank_fsm_tb: simulation FAILED");
        $finish;
    end

endmodule

results/phase-ddr4-bank/bank_fsm.vcd
$date
	Thu Mar 12 10:13:26 2026
$end
$version
	Icarus Verilog
$end
$timescale
	1ps
$end
$scope module bank_fsm_tb $end
$var wire 1 ! tras_ok $end
$var wire 2 " state_out [1:0] $end
$var wire 1 # row_active $end
$var wire 17 $ open_row [16:0] $end
$var wire 1 % fsm_ready $end
$var parameter 3 & CMD_ACT $end
$var parameter 3 ' CMD_NOP $end
$var parameter 3 ( CMD_PRE $end
$var parameter 3 ) CMD_RD $end
$var parameter 3 * CMD_WR $end
$var parameter 32 + P_TRAS $end
$var parameter 32 , P_TRCD $end
$var parameter 32 - P_TRP $end
$var parameter 32 . ROW_ADDR_W $end
$var parameter 2 / S_ACTIVATING $end
$var parameter 2 0 S_ACTIVE $end
$var parameter 2 1 S_IDLE $end
$var parameter 2 2 S_PRECHARGING $end
$var reg 1 3 clk $end
$var reg 3 4 cmd_in [2:0] $end
$var reg 1 5 cmd_valid $end
$var reg 17 6 row_addr_in [16:0] $end
$var reg 1 7 rst_n $end
$var reg 17 8 test_row [16:0] $end
$var integer 32 9 fail_count [31:0] $end
$var integer 32 : i [31:0] $end
$var integer 32 ; pass_count [31:0] $end
$scope module dut $end
$var wire 1 3 clk $end
$var wire 3 < cmd_in [2:0] $end
$var wire 1 5 cmd_valid $end
$var wire 17 = row_addr_in [16:0] $end
$var wire 1 7 rst_n $end
$var wire 1 ! tras_ok $end
$var parameter 3 > CMD_ACT $end
$var parameter 3 ? CMD_NOP $end
$var parameter 3 @ CMD_PRE $end
$var parameter 3 A CMD_RD $end
$var parameter 3 B CMD_REF $end
$var parameter 3 C CMD_WR $end
$var parameter 8 D INIT_TRAS $end
$var parameter 8 E INIT_TRCD $end
$var parameter 8 F INIT_TRP $end
$var parameter 32 G P_TRAS $end
$var parameter 32 H P_TRCD $end
$var parameter 32 I P_TRP $end
$var parameter 32 J ROW_ADDR_W $end
$var parameter 2 K S_ACTIVATING $end
$var parameter 2 L S_ACTIVE $end
$var parameter 2 M S_IDLE $end
$var parameter 2 N S_PRECHARGING $end
$var reg 1 % fsm_ready $end
$var reg 17 O open_row [16:0] $end
$var reg 1 # row_active $end
$var reg 2 P state [1:0] $end
$var reg 2 Q state_out [1:0] $end
$var reg 8 R tras_cnt [7:0] $end
$var reg 8 S trcd_cnt [7:0] $end
$var reg 8 T trp_cnt [7:0] $end
$upscope $end
$scope task chk $end
$var reg 1 U cond $end
$var reg 160 V msg [159:0] $end
$var reg 32 W test_id [31:0] $end
$upscope $end
$scope task idle_cycle $end
$upscope $end
$scope task send_cmd $end
$var reg 3 X c [2:0] $end
$var reg 17 Y raddr [16:0] $end
$upscope $end
$upscope $end
$enddefinitions $end
$comment Show the parameter values. $end
$dumpall
b11 N
b0 M
b10 L
b1 K
b10001 J
b100 I
b100 H
b1000 G
b10 F
b10 E
b111 D
b11 C
b101 B
b10 A
b100 @
b0 ?
b1 >
b11 2
b0 1
b10 0
b1 /
b10001 .
b100 -
b100 ,
b1000 +
b11 *
b10 )
b100 (
b0 '
b1 &
$end
#0
$dumpvars
bx Y
bx X
bx W
bx V
xU
b0 T
b0 S
b0 R
b0 Q
b0 P
b0 O
b0 =
b0 <
b0 ;
bx :
b0 9
bx 8
07
b0 6
05
b0 4
03
1%
b0 $
0#
b0 "
1!
$end
#5000
13
#10000
03
#15000
13
#20000
03
#25000
13
#30000
03
#35000
13
#36000
b100 ;
b111001001100101011100110110010101110100001110100010000001101111011100000110010101101110010111110111001001101111011101110011110100110000 V
b1 W
1U
#40000
03
#45000
13
#46000
17
#50000
03
#55000
13
#56000
b11010010110110011 Y
b1 X
b11010010110110011 8
#60000
15
b11010010110110011 6
b11010010110110011 =
b1 4
b1 <
03
#65000
b1 "
b1 Q
0%
b1 P
0!
b111 R
b10 S
b11010010110110011 $
b11010010110110011 O
13
#66000
b111 ;
b110111101110011011101000010110101000001010000110101010000111010001000000110011001110011011011010101111101110010011001010110000101100100011110010011110100110000 V
b10 W
05
#70000
b0 4
b0 <
03
#75000
b1 S
b110 R
13
#76000
b1001 ;
b100100101010110010000010101010001001001010011100100011100111010001000000110011001110011011011010101111101110010011001010110000101100100011110010011110100110000 V
b11 W
#80000
03
#85000
b0 S
b101 R
13
#86000
b1011 ;
b100100101010110010000010101010001001001010011100100011100111010001000000110011001110011011011010101111101110010011001010110000101100100011110010011110100110000 V
#90000
03
#95000
b10 "
b10 Q
1#
1%
b10 P
b100 R
13
#96000
b0 Y
b100 X
b100 W
b1111 ;
b110011001101001011001010110010000100000011011110110111000100000010000010100001101010100010010010101011001000101001000000110010101101110011101000111001001111001 V
#100000
15
b0 6
b0 =
b100 4
b100 <
03
#105000
b11 R
13
#106000
b11010010110110011 Y
b10 X
b10001 ;
b100000101010011001110100010000001110010011011110111011100100000011100110111010001101001011011000110110000100000011000010110001101110100011010010111011001100101 V
05
#110000
15
b11010010110110011 6
b11010010110110011 =
b10 4
b10 <
03
#115000
b10 R
13
#116000
b11 X
b10010 ;
b111001101110100011000010111010001100101001000000111001001100101011011010110000101101001011011100111001100100000010000010100001101010100010010010101011001000101 V
b101 W
05
#120000
15
b11 4
b11 <
03
#125000
b1 R
13
#126000
b0 :
b10011 ;
05
#130000
b0 4
b0 <
03
#135000
1!
b0 R
13
#136000
b0 Y
b100 X
b10100 ;
b111001101100001011101000110100101110011011001100110100101100101011001000011101000100000011101000111001001100001011100110101111101101111011010110011110100110001 V
b110 W
b1 :
#140000
15
b0 6
b0 =
b100 4
b100 <
03
#145000
b11 "
b11 Q
0#
0%
b11 P
b10 T
13
#146000
b10111 ;
b100000101010010010001110100100101001110010001110011101000100000011100100110111101110111010111110110000101100011011101000110100101110110011001010011110100110000 V
05
#150000
b0 4
b0 <
03
#155000
b1 T
13
#156000
b11001 ;
b100100001000001010100100100011101001001010011100100011100111010001000000110011001110011011011010101111101110010011001010110000101100100011110010011110100110000 V
b111 W
#160000
03
#165000
b0 T
13
#166000
b11011 ;
b100100001000001010100100100011101001001010011100100011100111010001000000110011001110011011011010101111101110010011001010110000101100100011110010011110100110000 V
#170000
03
#175000
b0 "
b0 Q
1%
b0 P
13
#176000
b1111000011110000 Y
b1 X
b1111000011110000 8
b11110 ;
b10010010100010001001100010001010011101000100000011100100110111101110111010111110110000101100011011101000110100101110110011001010011110100110000 V
b1000 W
#180000
15
b1111000011110000 6
b1111000011110000 =
b1 4
b1 <
03
#185000
b1 "
b1 Q
0%
b1 P
0!
b111 R
b10 S
b1111000011110000 $
b1111000011110000 O
13
#186000
b0 :
05
#190000
b0 4
b0 <
03
#195000
b1 S
b110 R
13
#196000
b1 :
#200000
03
#205000
b0 S
b101 R
13
#206000
b10 :
#210000
03
#215000
b10 "
b10 Q
1#
1%
b10 P
b100 R
13
#216000
b100000 ;
b110110001100101001110100010000001101111011100000110010101101110010111110111001001101111011101110010000001110101011100000110010001100001011101000110010101100100 V
b1001 W
b0 :
#220000
03
#225000
b11 R
13
#226000
b1 :
#230000
03
#235000
b10 R
13
#236000
b10 :
#240000
03
#245000
b1 R
13
#246000
b11 :
#250000
03
#255000
1!
b0 R
13
#256000
b0 Y
b100 X
b100 :
#260000
15
b0 6
b0 =
b100 4
b100 <
03
#265000
b11 "
b11 Q
0#
0%
b11 P
b10 T
13
#266000
b0 :
b100001 ;
b110010000100000011000110111100101100011011011000110010100111010001000000101000001010010010001010100001101001000010000010101001001000111010010010100111001000111 V
05
#270000
b0 4
b0 <
03
#275000
b1 T
13
#276000
b1 :
#280000
03
#285000
b0 T
13
#286000
b10 :
#290000
03
#295000
b0 "
b0 Q
1%
b0 P
13
#296000
b10010001101000101 Y
b1 X
b10010001101000101 8
b100010 ;
b10000001100011011110010110001101101100011001010011101000100000011000100110000101100011011010110010000001110100011011110010000001001001010001000100110001000101 V
b11 :
#300000
15
b10010001101000101 6
b10010001101000101 =
b1 4
b1 <
03
#305000
b1 "
b1 Q
0%
b1 P
0!
b111 R
b10 S
b10010001101000101 $
b10010001101000101 O
13
#306000
b0 :
05
#310000
b0 4
b0 <
03
#315000
b1 S
b110 R
13
#316000
b1 :
#320000
03
#325000
b0 S
b101 R
13
#326000
b10 :
#330000
03
#335000
b10 "
b10 Q
1#
1%
b10 P
b100 R
13
#336000
b10 X
b11 :
#340000
15
b10 4
b10 <
03
#345000
b11 R
13
#346000
05
#350000
15
03
#355000
b10 R
13
#356000
05
#360000
15
03
#365000
b1 R
13
#366000
05
#370000
15
03
#375000
1!
b0 R
13
#376000
b100100 ;
b100100101010110010001010010000001100001011000110111001001101111011100110111001100100000010100100100010000100000011000100111010101110010011100110111010001110011 V
b1010 W
05
